Workbook

Sheet Sheet2
A3: Row Labels | B3: Sum of Revenue Amount
A4: Q1 2021 | B4: 0
A5: Q1 2022 | B5: 683333
A6: Q1 2023 | B6: 350378
A7: Q2 2022 | B7: 1517746
A8: Q2 2023 | B8: 253426
A9: Q3 2021 | B9: 125657
A10: Q3 2022 | B10: 1331365
A11: Q3 2023 | B11: 54683
A12: Q4 2021 | B12: 32392
A13: Q4 2022 | B13: 4327919
A14: Grand Total | B14: 8676899
A19: Sum of Potential Business | B19: Column Labels
A20: Row Labels | B20: Austria | C20: Bulgaria | D20: Czech Republic | E20: Denmark | F20: Finland | G20: France | H20: Germany | I20: Gibraltar | J20: Hungary | K20: Italy | L20: Liechtenstein | M20: Malaysia | N20: Monaco | O20: Poland | P20: Portugal | Q20: Romania | R20: San Marino | S20: Slovakia | T20: Spain | U20: Sweden | V20: Switzerland | W20: United Kingdom | X20: USA | Y20: Grand Total
A21: 20145 | K21: 157233 | Y21: 157233
A22: 20864 | K22: 91793 | Y22: 91793
A23: 35010 | K23: 184680 | Y23: 184680
A24: 36100 | K24: 99211 | Y24: 99211
A25: (BERGAMO) CENATE SOTTO | K25: 30902 | Y25: 30902
A26: ?Ravenna | K26: 120138 | Y26: 120138
A27: 1600-079 | P27: 63020 | Y27: 63020
A28: A CORUNA | T28: 158554 | Y28: 158554
A29: A Coruña | T29: 106692 | Y29: 106692
A30: Aachen | H30: 545216 | Y30: 545216
A31: ABANO TERME | K31: 50316 | Y31: 50316
A32: Achim | H32: 57380 | Y32: 57380
A33: Aci Castello | K33: 109545 | Y33: 109545
A34: Aerzen | H34: 150659 | Y34: 150659
A35: Ahaus | H35: 52325 | Y35: 52325
A36: Ahrensburg | H36: 349968 | Y36: 349968
A37: Aix en Provence | G37: 97965 | Y37: 97965
A38: Aix-en-Provence | G38: 157181 | Y38: 157181
A39: Alba | K39: 132337 | Y39: 132337
A40: Albalat De La Ribera | T40: 87037 | Y40: 87037
A41: Albi | G41: 67064 | Y41: 67064
A42: Albino | K42: 77466 | Y42: 77466
A43: Albstadt | H43: 139350 | Y43: 139350
A44: Alcalá de Henares | T44: 108983 | Y44: 108983
A45: ALCOBENDAS | T45: 1113702 | Y45: 1113702
A46: Alcorcón - Madrid | T46: 83580 | Y46: 83580
A47: ALCOY/ALCOI | T47: 76983 | Y47: 76983
A48: ALCUDIA | T48: 56858 | Y48: 56858
A49: ALGECIRAS | T49: 32000 | Y49: 32000
A50: Alhama de Murcia | T50: 80523 | Y50: 80523
A51: Alicante | T51: 557324 | Y51: 557324
A52: ALICANTE/ALACANT | T52: 80523 | Y52: 80523
A53: Allendorf (Eder) | H53: 315568 | Y53: 315568
A54: Allmersbach im Tal | H54: 373568 | Y54: 373568
A55: Alsasua | T55: 143517 | Y55: 143517
A56: Alsdorf | H56: 181209 | Y56: 181209
A57: Altavilla Vicentina | K57: 277565 | Y57: 277565
A58: Amberieu En Bugey | G58: 115471 | Y58: 115471
A59: Amstetten | B59: 77562 | Y59: 77562
A60: Ancona | K60: 80575 | Y60: 80575
A61: Angri | K61: 77640 | Y61: 77640
A62: ANZOLA DELL'EMILIA | K62: 77515 | Y62: 77515
A63: Anzola Emilia | K63: 116939 | Y63: 116939
A64: Aosta | K64: 141076 | Y64: 141076
A65: Aranjuez | T65: 104166 | Y65: 104166
A66: Arco di Trento | K66: 101487 | Y66: 101487
A67: Arese | K67: 65114 | Y67: 65114
A68: Arezzo | K68: 74058 | Y68: 74058
A69: Arganda del rey | T69: 122068 | Y69: 122068
A70: Argentona | T70: 107069 | Y70: 107069
A71: ARQUES | G71: 40191 | Y71: 40191
A72: Arrabaldo | T72: 187470 | Y72: 187470
A73: ARZIGNANO | K73: 69907 | Y73: 69907
A74: Aschheim | H74: 49486 | Y74: 49486
A75: Ascoli Piceno | K75: 99320 | Y75: 99320
A76: Asnières sur seine | G76: 110043 | Y76: 110043
A77: Asolo
A78: Assago | K78: 112714 | Y78: 112714
A79: Asturias | T79: 54725 | Y79: 54725
A80: Augsburg | H80: 338397 | Y80: 338397
A81: Auna di Sotto/Renon | K81: 132000 | Y81: 132000
A82: Avellino | K82: 101449 | Y82: 101449
A83: AVIGLIANA | K83: 128110 | Y83: 128110
A84: Baar | V84: 98316 | Y84: 98316
A85: Bad Bevensen | H85: 96601 | Y85: 96601
A86: Bad Dürkheim | H86: 146799 | Y86: 146799
A87: Bad Fallingbos | H87: 149219 | Y87: 149219
A88: Bad Homburg | H88: 311129 | Y88: 311129
A89: Bad Neustadt
A90: Bad Rodach | H90: 366022 | Y90: 366022
A91: Bad Salzungen / OT Langenfeld | H91: 94769 | Y91: 94769
A92: Bad Waldsee | H92: 400793 | Y92: 400793
A93: Badalona | T93: 172921 | Y93: 172921
A94: Bagnolet | G94: 100035 | Y94: 100035
A95: Bagnolo in piano | K95: 121680 | Y95: 121680
A96: Balzers | L96: 237786 | Y96: 237786
A97: Baranzate | K97: 100528 | Y97: 100528
A98: Barcelon | T98: 55037 | Y98: 55037
A99: Barcelona | T99: 9977693 | Y99: 9977693
A100: Barga | K100: 120380 | Y100: 120380
A101: Bargteheide | H101: 130735 | Y101: 130735
A102: Barletta | K102: 122985 | Y102: 122985
A103: Basauri | T103: 488468 | Y103: 488468
A104: Basel | V104: 80117 | Y104: 80117
A105: BASSANO DEL GRAPPA | K105: 214575 | Y105: 214575
A106: Bayreuth | H106: 71090 | Y106: 71090
...

Sheet Sales Data
A1: Account Name | B1: Account Status | C1: Future Growth Potential Segment | D1: Account Owner | E1: Primary Country | F1: Primary City | G1: Potential Business | H1: Opportunity Start date | I1: Revenue Amount | J1: Opportunity Close Date | K1: Quarter and Year wrt Close date | L1: Column1 | M1: Column13 | N1: Column14
A2: Antai Venture Builder | B2: Not a Customer | C2: No growth Potential | D2: Roman Nacha | E2: Spain | F2: Barcelona | G2: 116997 | H2: 13-03-2022 | I2: 0 | J2: 44596 | K2: ="Q" & ROUNDUP(MONTH(J:J)/3,0) & " " & YEAR(J:J) -> Q1 2022 | L2: ="Q" & ROUNDUP(MONTH(J:J)/3,0) & " " & YEAR(J:J) -> Q1 2022
A3: Grupo LoMonaco | B3: Not a Customer | C3: No growth Potential | D3: Roman Nacha | E3: Spain | F3: Peligros | G3: 143588 | H3: 44630 | I3: 0 | J3: 44604 | K3: ="Q" & ROUNDUP(MONTH(J:J)/3,0) & " " & YEAR(J:J) -> Q1 2022 | L3: ="Q" & ROUNDUP(MONTH(J:J)/3,0) & " " & YEAR(J:J) -> Q1 2022
A4: WEB IDEIAS - SERVICOS DE INTERNET SOCIEDADE UNIPESSOAL LDA | B4: Active Customer | C4: High Growth potential | D4: Roman Nacha | E4: Portugal | F4: Vila das Aves | G4: 61002 | H4: 44572 | I4: 12200 | J4: 44876 | K4: ="Q" & ROUNDUP(MONTH(J:J)/3,0) & " " & YEAR(J:J) -> Q4 2022 | L4: ="Q" & ROUNDUP(MONTH(J:J)/3,0) & " " & YEAR(J:J) -> Q4 2022
A5: Simon S.A. | B5: Not a Customer | C5: No growth Potential | D5: Roman Nacha | E5: Spain | F5: Barcelona | G5: 109980 | H5: 23-10-2022 | I5: 0 | J5: 44603 | K5: ="Q" & ROUNDUP(MONTH(J:J)/3,0) & " " & YEAR(J:J) -> Q1 2022 | L5: ="Q" & ROUNDUP(MONTH(J:J)/3,0) & " " & YEAR(J:J) -> Q1 2022 | Q5: Total Potential | R5: =SUM(G:G) -> 263143746
A6: Civitatis | B6: Active Customer | C6: High Growth potential | D6: Roman Nacha | E6: Spain | F6: Madrid | G6: 106526 | H6: 44601 | I6: 53263 | J6: 44602 | K6: ="Q" & ROUNDUP(MONTH(J:J)/3,0) & " " & YEAR(J:J) -> Q1 2022 | L6: ="Q" & ROUNDUP(MONTH(J:J)/3,0) & " " & YEAR(J:J) -> Q1 2022 | Q6: Total Revenue | R6: =SUM(I:I) -> 8676899
A7: AJUNTAMENT DE TARRAGONA | B7: Not a Customer | C7: No growth Potential | D7: Roman Nacha | E7: Spain | F7: Tarragona | G7: 70969 | H7: 13-09-2022 | I7: 0 | J7: 44603 | K7: ="Q" & ROUNDUP(MONTH(J:J)/3,0) & " " & YEAR(J:J) -> Q1 2022 | L7: ="Q" & ROUNDUP(MONTH(J:J)/3,0) & " " & YEAR(J:J) -> Q1 2022 | P7: Entire -> | Q7: Conversion rate | R7: =COUNTIF(B:B, "Active Customer") / COUNTA(B:B) * 100 -> 11.323603
A8: KAVE HOME | B8: Not a Customer | C8: No growth Potential | D8: Roman Nacha | E8: Spain | F8: GIRONA | G8: 100034 | H8: 44632 | I8: 0 | J8: 44958 | K8: ="Q" & ROUNDUP(MONTH(J:J)/3,0) & " " & YEAR(J:J) -> Q1 2023 | L8: ="Q" & ROUNDUP(MONTH(J:J)/3,0) & " " & YEAR(J:J) -> Q1 2023 | Q8: Active Customers | R8: =COUNTIF(B:B, "Active Customer") -> 225
A9: Camara Municipal de Cascais | B9: Not a Customer | C9: No growth Potential | D9: Roman Nacha | E9: Portugal | F9: Cascais | G9: 107069 | H9: 21-10-2022 | I9: 0 | J9: 20-11-2022 | K9: ="Q" & ROUNDUP(MONTH(J:J)/3,0) & " " & YEAR(J:J) -> Q4 2022 | L9: ="Q" & ROUNDUP(MONTH(J:J)/3,0) & " " & YEAR(J:J) -> Q4 2022 | Q9: Not a Customer | R9: =COUNTIF(B:B, "Not a Customer") -> 1761
A10: MERCEDES BENZ ESPANA S.A | B10: Not a Customer | C10: No growth Potential | D10: Roman Nacha | E10: Spain | F10: ALCOBENDAS | G10: 143517 | H10: 13-10-2022 | I10: 0 | J10: 44603 | K10: ="Q" & ROUNDUP(MONTH(J:J)/3,0) & " " & YEAR(J:J) -> Q1 2022 | L10: ="Q" & ROUNDUP(MONTH(J:J)/3,0) & " " & YEAR(J:J) -> Q1 2022 | Q10: kaityu Bonolam | R10: =COUNTIFS(D:D, "Kaityu Bonolam", B:B, "Active Customer") / COUNTIF(D:D, "Kaityu Bonolam") * 100 -> 82.666667
A11: Vilau Media | B11: Not a Customer | C11: No growth Potential | D11: Roman Nacha | E11: Spain | F11: Erandio | G11: 58504 | H11: 24-08-2022 | I11: 0 | J11: 44603 | K11: ="Q" & ROUNDUP(MONTH(J:J)/3,0) & " " & YEAR(J:J) -> Q1 2022 | L11: ="Q" & ROUNDUP(MONTH(J:J)/3,0) & " " & YEAR(J:J) -> Q1 2022 | Q11: Roman Nacha | R11: =COUNTIFS(D:D, "Roman Nacha", B:B, "Active Customer") / COUNTIF(D:D, "Roman Nacha") * 100 -> 5.9556787
A12: Genetsis & Partners S.A. | B12: Not a Customer | C12: No growth Potential | D12: Roman Nacha | E12: Spain | F12: Alcobendas | G12: 95966 | H12: 23-10-2022 | I12: 0 | J12: 44603 | K12: ="Q" & ROUNDUP(MONTH(J:J)/3,0) & " " & YEAR(J:J) -> Q1 2022 | L12: ="Q" & ROUNDUP(MONTH(J:J)/3,0) & " " & YEAR(J:J) -> Q1 2022 | Q12: Ban Roamer | R12: =COUNTIFS(D:D, "Ban Roamer", B:B, "Active Customer") / COUNTIF(D:D, "Ban Roamer") * 100 -> 6.127451
A13: Gobierno de Portugal | B13: Not a Customer | C13: No growth Potential | D13: Roman Nacha | E13: Portugal | F13: TBD | G13: 54725 | H13: 23-10-2022 | I13: 0 | J13: 44603 | K13: ="Q" & ROUNDUP(MONTH(J:J)/3,0) & " " & YEAR(J:J) -> Q1 2022 | L13: ="Q" & ROUNDUP(MONTH(J:J)/3,0) & " " & YEAR(J:J) -> Q1 2022 | Q13: Naz ismail | R13: =COUNTIFS(D:D, "Naz ismail", B:B, "Active Customer") / COUNTIF(D:D, "Naz ismail") * 100 -> 7.4340528
A14: PUERTOS DEL ESTADO | B14: Not a Customer | C14: High Growth potential | D14: Roman Nacha | E14: Spain | F14: Madrid | G14: 147868 | H14: 19-09-2022 | I14: 0 | J14: 44784 | K14: ="Q" & ROUNDUP(MONTH(J:J)/3,0) & " " & YEAR(J:J) -> Q3 2022 | L14: ="Q" & ROUNDUP(MONTH(J:J)/3,0) & " " & YEAR(J:J) -> Q3 2022 | Q14: Ben Usioka | R14: =COUNTIFS(D:D, "Ben Usioka", B:B, "Active Customer") / COUNTIF(D:D, "Ben Usioka") * 100 -> 71.875
A15: PRA Iberia | B15: Not a Customer | C15: No growth Potential | D15: Roman Nacha | E15: Spain | F15: Madrid | G15: 112714 | H15: 22-12-2022 | I15: 0 | J15: 44960 | K15: ="Q" & ROUNDUP(MONTH(J:J)/3,0) & " " & YEAR(J:J) -> Q1 2023 | L15: ="Q" & ROUNDUP(MONTH(J:J)/3,0) & " " & YEAR(J:J) -> Q1 2023 | Q15: Country Revenue = Germnay | R15: =SUMIFS(I:I, E:E, "Germany") -> 4039839
A16: INSTITUTO DE MURCIA | B16: Not a Customer | C16: No growth Potential | D16: Roman Nacha | E16: Spain | F16: Murcia | G16: 74208 | H16: 19-02-2022 | I16: 0 | J16: 20-04-2022 | K16: ="Q" & ROUNDUP(MONTH(J:J)/3,0) & " " & YEAR(J:J) -> Q2 2022 | L16: ="Q" & ROUNDUP(MONTH(J:J)/3,0) & " " & YEAR(J:J) -> Q2 2022 | Q16: Revenue -> Spain | R16: =SUMIF(E:E, "Spain", I:I) -> 1398148
A17: Multiestetica | B17: Not a Customer | C17: No growth Potential | D17: Roman Nacha | E17: Spain | F17: TBD | G17: 90068 | H17: 44629 | I17: 0 | J17: 44603 | K17: ="Q" & ROUNDUP(MONTH(J:J)/3,0) & " " & YEAR(J:J) -> Q1 2022 | L17: ="Q" & ROUNDUP(MONTH(J:J)/3,0) & " " & YEAR(J:J) -> Q1 2022 | Q17: Spain -> Accounts | R17: =COUNTIF(E:E, "Spain") -> 658
A18: Defensor del Pueblo | B18: Active Customer | C18: Medium Growth | D18: Roman Nacha | E18: Spain | F18: Madrid | G18: 80085 | H18: 44571 | I18: 40042 | J18: 20-11-2022 | K18: ="Q" & ROUNDUP(MONTH(J:J)/3,0) & " " & YEAR(J:J) -> Q4 2022 | L18: ="Q" & ROUNDUP(MONTH(J:J)/3,0) & " " & YEAR(J:J) -> Q4 2022 | Q18: Active Customers in Spain | R18: =COUNTIFS(E:E, "Spain", B:B, "Active Customer") -> 40
A19: INFOJOBS S.A. | B19: Not a Customer | C19: No growth Potential | D19: Roman Nacha | E19: Spain | F19: BARCELONA | G19: 157857 | H19: 24-08-2022 | I19: 0 | J19: 44603 | K19: ="Q" & ROUNDUP(MONTH(J:J)/3,0) & " " & YEAR(J:J) -> Q1 2022 | L19: ="Q" & ROUNDUP(MONTH(J:J)/3,0) & " " & YEAR(J:J) -> Q1 2022 | Q19: High Growth Potential | R19: =COUNTIF(C:C, "High Growth Potential") -> 151
A20: COSTAISA | B20: Not a Customer | C20: No growth Potential | D20: Roman Nacha | E20: Spain | F20: BARCELONA | G20: 88677 | H20: 23-10-2022 | I20: 0 | J20: 44603 | K20: ="Q" & ROUNDUP(MONTH(J:J)/3,0) & " " & YEAR(J:J) -> Q1 2022 | L20: ="Q" & ROUNDUP(MONTH(J:J)/3,0) & " " & YEAR(J:J) -> Q1 2022
A21: CTT Correios | B21: Not a Customer | C21: No growth Potential | D21: Roman Nacha | E21: Portugal | F21: Oporto | G21: 203793 | H21: 44629 | I21: 0 | J21: 44603 | K21: ="Q" & ROUNDUP(MONTH(J:J)/3,0) & " " & YEAR(J:J) -> Q1 2022 | L21: ="Q" & ROUNDUP(MONTH(J:J)/3,0) & " " & YEAR(J:J) -> Q1 2022
A22: ServoTIC | B22: Not a Customer | C22: No growth Potential | D22: Roman Nacha | E22: Spain | F22: Madrid | G22: 55037 | H22: 23-10-2022 | I22: 0 | J22: 44603 | K22: ="Q" & ROUNDUP(MONTH(J:J)/3,0) & " " & YEAR(J:J) -> Q1 2022 | L22: ="Q" & ROUNDUP(MONTH(J:J)/3,0) & " " & YEAR(J:J) -> Q1 2022
A23: ATRAPALO S.L. | B23: Active Customer | C23: High Growth potential | D23: Roman Nacha | E23: Spain | F23: Barcelona | G23: 106786 | H23: 19-10-2022 | I23: 53393 | J23: 44784 | K23: ="Q" & ROUNDUP(MONTH(J:J)/3,0) & " " & YEAR(J:J) -> Q3 2022 | L23: ="Q" & ROUNDUP(MONTH(J:J)/3,0) & " " & YEAR(J:J) -> Q3 2022
A24: Customs & Global Trade at Caro Jaume & Partners | B24: Not a Customer | C24: No growth Potential | D24: Roman Nacha | E24: Spain | F24: Madrid | G24: 83160 | H24: 45231 | I24: 0 | J24: 44960 | K24: ="Q" & ROUNDUP(MONTH(J:J)/3,0) & " " & YEAR(J:J) -> Q1 2023 | L24: ="Q" & ROUNDUP(MONTH(J:J)/3,0) & " " & YEAR(J:J) -> Q1 2023
A25: Roca Corporacion Empresarial S.A. | B25: Active Customer | C25: Medium Growth | D25: Roman Nacha | E25: Spain | F25: Barcelona | G25: 137608 | H25: 31-03-2022 | I25: 9829 | J25: 20-04-2022 | K25: ="Q" & ROUNDUP(MONTH(J:J)/3,0) & " " & YEAR(J:J) -> Q2 2022 | L25: ="Q" & ROUNDUP(MONTH(J:J)/3,0) & " " & YEAR(J:J) -> Q2 2022
A26: LACTALIS PULEVA S.L | B26: Not a Customer | C26: No growth Potential | D26: Roman Nacha | E26: Spain | F26: Granada | G26: 157835 | H26: 23-09-2022 | I26: 0 | J26: 44603 | K26: ="Q" & ROUNDUP(MONTH(J:J)/3,0) & " " & YEAR(J:J) -> Q1 2022 | L26: ="Q" & ROUNDUP(MONTH(J:J)/3,0) & " " & YEAR(J:J) -> Q1 2022
A27: GRUPO COREN | B27: Not a Customer | C27: High Growth potential | D27: Roman Nacha | E27: Spain | F27: Arrabaldo | G27: 187470 | H27: 23-10-2022 | I27: 0 | J27: 44603 | K27: ="Q" & ROUNDUP(MONTH(J:J)/3,0) & " " & YEAR(J:J) -> Q1 2022 | L27: ="Q" & ROUNDUP(MONTH(J:J)/3,0) & " " & YEAR(J:J) -> Q1 2022
A28: Transportes Boyaca S.L. | B28: Not a Customer | C28: High Growth potential | D28: Roman Nacha | E28: Spain | F28: TBD | G28: 102196 | H28: 20-02-2022 | I28: 0 | J28: 44595 | K28: ="Q" & ROUNDUP(MONTH(J:J)/3,0) & " " & YEAR(J:J) -> Q1 2022 | L28: ="Q" & ROUNDUP(MONTH(J:J)/3,0) & " " & YEAR(J:J) -> Q1 2022
A29: AXPE CONSULTING | B29: Not a Customer | C29: High Growth potential | D29: Roman Nacha | E29: Spain | F29: TBD | G29: 100539 | H29: 13-10-2022 | I29: 0 | J29: 44603 | K29: ="Q" & ROUNDUP(MONTH(J:J)/3,0) & " " & YEAR(J:J) -> Q1 2022 | L29: ="Q" & ROUNDUP(MONTH(J:J)/3,0) & " " & YEAR(J:J) -> Q1 2022
A30: BÓBOLI | B30: Not a Customer | C30: No growth Potential | D30: Roman Nacha | E30: Spain | F30: Llinars del Valles | G30: 76925 | H30: 24-08-2022 | I30: 0 | J30: 44603 | K30: ="Q" & ROUNDUP(MONTH(J:J)/3,0) & " " & YEAR(J:J) -> Q1 2022 | L30: ="Q" & ROUNDUP(MONTH(J:J)/3,0) & " " & YEAR(J:J) -> Q1 2022
A31: Modasystem srl | B31: Not a Customer | C31: No growth Potential | D31: Roman Nacha | E31: Italy | F31: BASSANO DEL GRAPPA | G31: 110085 | H31: 23-03-2022 | I31: 0 | J31: 44596 | K31: ="Q" & ROUNDUP(MONTH(J:J)/3,0) & " " & YEAR(J:J) -> Q1 2022 | L31: ="Q" & ROUNDUP(MONTH(J:J)/3,0) & " " & YEAR(J:J) -> Q1 2022
A32: Imaste IPS | B32: Not a Customer | C32: No growth Potential | D32: Roman Nacha | E32: Spain | F32: TBD | G32: 83580 | H32: 44836 | I32: 0 | J32: 44595 | K32: ="Q" & ROUNDUP(MONTH(J:J)/3,0) & " " & YEAR(J:J) -> Q1 2022 | L32: ="Q" & ROUNDUP(MONTH(J:J)/3,0) & " " & YEAR(J:J) -> Q1 2022
A33: PARQUE DE ATRACCIONES MADRID SA | B33: Not a Customer | C33: No growth Potential | D33: Roman Nacha | E33: Spain | F33: MADRID | H33: 23-10-2022 | I33: 0 | J33: 44603 | K33: ="Q" & ROUNDUP(MONTH(J:J)/3,0) & " " & YEAR(J:J) -> Q1 2022 | L33: ="Q" & ROUNDUP(MONTH(J:J)/3,0) & " " & YEAR(J:J) -> Q1 2022
A34: Fundacion Tripartita | B34: Not a Customer | C34: High Growth potential | D34: Roman Nacha | E34: Spain | F34: Madrid | G34: 42045 | H34: 13-03-2022 | I34: 0 | J34: 44597 | K34: ="Q" & ROUNDUP(MONTH(J:J)/3,0) & " " & YEAR(J:J) -> Q1 2022 | L34: ="Q" & ROUNDUP(MONTH(J:J)/3,0) & " " & YEAR(J:J) -> Q1 2022
A35: Optimus Zero SA (OPTIZE) | B35: Not a Customer | C35: No growth Potential | D35: Roman Nacha | E35: Spain | F35: Madrid | G35: 72988 | H35: 23-09-2022 | I35: 0 | J35: 44603 | K35: ="Q" & ROUNDUP(MONTH(J:J)/3,0) & " " & YEAR(J:J) -> Q1 2022 | L35: ="Q" & ROUNDUP(MONTH(J:J)/3,0) & " " & YEAR(J:J) -> Q1 2022
A36: CAP GEMINI ESPA?A S.A. | B36: Not a Customer | C36: No growth Potential | D36: Roman Nacha | E36: Spain | F36: MADRID | G36: 203733 | H36: 44630 | I36: 0 | J36: 44603 | K36: ="Q" & ROUNDUP(MONTH(J:J)/3,0) & " " & YEAR(J:J) -> Q1 2022 | L36: ="Q" & ROUNDUP(MONTH(J:J)/3,0) & " " & YEAR(J:J) -> Q1 2022
A37: CONGRESO DE LOS DIPUTADOS | B37: Active Customer | C37: Medium Growth | D37: Roman Nacha | E37: Spain | F37: Madrid | G37: 172921 | H37: 44813 | I37: 9607 | J37: 44784 | K37: ="Q" & ROUNDUP(MONTH(J:J)/3,0) & " " & YEAR(J:J) -> Q3 2022 | L37: ="Q" & ROUNDUP(MONTH(J:J)/3,0) & " " & YEAR(J:J) -> Q3 2022
A38: Amb Molt d' Encert S.L | B38: Not a Customer | C38: No growth Potential | D38: Roman Nacha | E38: Spain | F38: TBD | G38: 56858 | H38: 23-10-2022 | I38: 0 | J38: 44603 | K38: ="Q" & ROUNDUP(MONTH(J:J)/3,0) & " " & YEAR(J:J) -> Q1 2022 | L38: ="Q" & ROUNDUP(MONTH(J:J)/3,0) & " " & YEAR(J:J) -> Q1 2022
A39: GERMAINE DE CAPUCCINI | B39: Not a Customer | C39: No growth Potential | D39: Roman Nacha | E39: Spain | F39: ALCOY/ALCOI | G39: 76983 | H39: 22-09-2022 | I39: 0 | J39: 44602 | K39: ="Q" & ROUNDUP(MONTH(J:J)/3,0) & " " & YEAR(J:J) -> Q1 2022 | L39: ="Q" & ROUNDUP(MONTH(J:J)/3,0) & " " & YEAR(J:J) -> Q1 2022
A40: Woyre | B40: Not a Customer | C40: No growth Potential | D40: Roman Nacha | E40: Spain | F40: TBD | G40: 43881 | H40: 44630 | I40: 0 | J40: 44603 | K40: ="Q" & ROUNDUP(MONTH(J:J)/3,0) & " " & YEAR(J:J) -> Q1 2022 | L40: ="Q" & ROUNDUP(MONTH(J:J)/3,0) & " " & YEAR(J:J) -> Q1 2022
A41: Gecesa Cajamadrid | B41: Not a Customer | C41: Medium Growth | D41: Roman Nacha | E41: Spain | F41: madrid | G41: 88013 | H41: 23-11-2022 | I41: 0 | J41: 44958 | K41: ="Q" & ROUNDUP(MONTH(J:J)/3,0) & " " & YEAR(J:J) -> Q1 2023 | L41: ="Q" & ROUNDUP(MONTH(J:J)/3,0) & " " & YEAR(J:J) -> Q1 2023
A42: My Crypto Bot | B42: Not a Customer | C42: Medium Growth | D42: Roman Nacha | E42: Spain | F42: TBD | G42: 92126 | H42: 44875 | I42: 0 | J42: 20-11-2022 | K42: ="Q" & ROUNDUP(MONTH(J:J)/3,0) & " " & YEAR(J:J) -> Q4 2022 | L42: ="Q" & ROUNDUP(MONTH(J:J)/3,0) & " " & YEAR(J:J) -> Q4 2022
A43: Venca (C.I.F.D.S.A) | B43: Not a Customer | C43: No growth Potential | D43: Roman Nacha | E43: Spain | F43: Vilanova I La Geltru | G43: 106692 | H43: 24-08-2022 | I43: 0 | J43: 44603 | K43: ="Q" & ROUNDUP(MONTH(J:J)/3,0) & " " & YEAR(J:J) -> Q1 2022 | L43: ="Q" & ROUNDUP(MONTH(J:J)/3,0) & " " & YEAR(J:J) -> Q1 2022
A44: AYUNTAMIENTO DE GIJON | B44: Not a Customer | C44: No growth Potential | D44: Roman Nacha | E44: Spain | F44: GIJON | G44: 133858 | H44: 23-09-2022 | I44: 0 | J44: 44603 | K44: ="Q" & ROUNDUP(MONTH(J:J)/3,0) & " " & YEAR(J:J) -> Q1 2022 | L44: ="Q" & ROUNDUP(MONTH(J:J)/3,0) & " " & YEAR(J:J) -> Q1 2022
A45: Ayuntamiento de Madrid | B45: Active Customer | C45: Medium Growth | D45: Roman Nacha | E45: Spain | F45: MADRID | G45: 368455 | H45: 13-09-2022 | I45: 46057 | J45: 44603 | K45: ="Q" & ROUNDUP(MONTH(J:J)/3,0) & " " & YEAR(J:J) -> Q1 2022 | L45: ="Q" & ROUNDUP(MONTH(J:J)/3,0) & " " & YEAR(J:J) -> Q1 2022
A46: Iberojet | B46: Not a Customer | C46: No growth Potential | D46: Roman Nacha | E46: Spain | F46: PALMA | G46: 107211 | H46: 13-09-2022 | I46: 0 | J46: 44603 | K46: ="Q" & ROUNDUP(MONTH(J:J)/3,0) & " " & YEAR(J:J) -> Q1 2022 | L46: ="Q" & ROUNDUP(MONTH(J:J)/3,0) & " " & YEAR(J:J) -> Q1 2022
A47: Azbil Telstar Technologies S.L.U. | B47: Not a Customer | C47: No growth Potential | D47: Roman Nacha | E47: Spain | F47: TERRASSA | G47: 115087 | H47: 44813 | I47: 0 | J47: 44784 | K47: ="Q" & ROUNDUP(MONTH(J:J)/3,0) & " " & YEAR(J:J) -> Q3 2022 | L47: ="Q" & ROUNDUP(MONTH(J:J)/3,0) & " " & YEAR(J:J) -> Q3 2022
A48: AYUNTAMIENTO DE ARANJUEZ | B48: Not a Customer | C48: No growth Potential | D48: Roman Nacha | E48: Spain | F48: Aranjuez | G48: 104166 | H48: 44927 | I48: 0 | J48: 44960 | K48: ="Q" & ROUNDUP(MONTH(J:J)/3,0) & " " & YEAR(J:J) -> Q1 2023 | L48: ="Q" & ROUNDUP(MONTH(J:J)/3,0) & " " & YEAR(J:J) -> Q1 2023
A49: Lamas Bolaño | B49: Not a Customer | C49: No growth Potential | D49: Roman Nacha | E49: Spain | F49: TBD | G49: 143497 | H49: 21-03-2022 | I49: 0 | J49: 20-04-2022 | K49: ="Q" & ROUNDUP(MONTH(J:J)/3,0) & " " & YEAR(J:J) -> Q2 2022 | L49: ="Q" & ROUNDUP(MONTH(J:J)/3,0) & " " & YEAR(J:J) -> Q2 2022
A50: Luis Simoes | B50: Not a Customer | C50: No growth Potential | D50: Roman Nacha | E50: Portugal | F50: CARREGADO | G50: 127427 | H50: 44630 | I50: 0 | J50: 44603 | K50: ="Q" & ROUNDUP(MONTH(J:J)/3,0) & " " & YEAR(J:J) -> Q1 2022 | L50: ="Q" & ROUNDUP(MONTH(J:J)/3,0) & " " & YEAR(J:J) -> Q1 2022
A51: Consum Sociedad Cooperativa Valenciana | B51: Not a Customer | C51: No growth Potential | D51: Roman Nacha | E51: Spain | F51: Silla | G51: 355370 | H51: 13-01-2023 | I51: 0 | J51: 44959 | K51: ="Q" & ROUNDUP(MONTH(J:J)/3,0) & " " & YEAR(J:J) -> Q1 2023 | L51: ="Q" & ROUNDUP(MONTH(J:J)/3,0) & " " & YEAR(J:J) -> Q1 2023
A52: GRUPO IFA | B52: Not a Customer | C52: No growth Potential | D52: Roman Nacha | E52: Spain | F52: Alcobendas | G52: 191190 | H52: 24-08-2022 | I52: 0 | J52: 44603 | K52: ="Q" & ROUNDUP(MONTH(J:J)/3,0) & " " & YEAR(J:J) -> Q1 2022 | L52: ="Q" & ROUNDUP(MONTH(J:J)/3,0) & " " & YEAR(J:J) -> Q1 2022
A53: Silgan Dispensing Systems Barcelona SL | B53: Not a Customer | C53: No growth Potential | D53: Roman Nacha | E53: Spain | F53: Barcelona | G53: 209817 | H53: 23-03-2022 | I53: 0 | J53: 44597 | K53: ="Q" & ROUNDUP(MONTH(J:J)/3,0) & " " & YEAR(J:J) -> Q1 2022 | L53: ="Q" & ROUNDUP(MONTH(J:J)/3,0) & " " & YEAR(J:J) -> Q1 2022
A54: Colomer Escuela náutica | B54: Not a Customer | C54: No growth Potential | D54: Roman Nacha | E54: Spain | F54: Cabo de Palos | G54: 49625 | H54: 21-01-2023 | I54: 0 | J54: 44960 | K54: ="Q" & ROUNDUP(MONTH(J:J)/3,0) & " " & YEAR(J:J) -> Q1 2023 | L54: ="Q" & ROUNDUP(MONTH(J:J)/3,0) & " " & YEAR(J:J) -> Q1 2023
A55: Safelayer | B55: Not a Customer | C55: No growth Potential | D55: Roman Nacha | E55: Spain | F55: Madrid | G55: 101488 | H55: 14-12-2021 | I55: 0 | J55: 44594 | K55: ="Q" & ROUNDUP(MONTH(J:J)/3,0) & " " & YEAR(J:J) -> Q1 2022 | L55: ="Q" & ROUNDUP(MONTH(J:J)/3,0) & " " & YEAR(J:J) -> Q1 2022
A56: IRIUM NETWORKS S.L. | B56: Not a Customer | C56: No growth Potential | D56: Roman Nacha | E56: Spain | F56: BARCELONA | G56: 101400 | H56: 23-09-2022 | I56: 0 | J56: 44603 | K56: ="Q" & ROUNDUP(MONTH(J:J)/3,0) & " " & YEAR(J:J) -> Q1 2022 | L56: ="Q" & ROUNDUP(MONTH(J:J)/3,0) & " " & YEAR(J:J) -> Q1 2022
A57: Liz Online | B57: Not a Customer | C57: No growth Potential | D57: Roman Nacha | E57: Portugal | F57: TBD | G57: 67715 | H57: 23-10-2022 | I57: 0 | J57: 44603 | K57: ="Q" & ROUNDUP(MONTH(J:J)/3,0) & " " & YEAR(J:J) -> Q1 2022 | L57: ="Q" & ROUNDUP(MONTH(J:J)/3,0) & " " & YEAR(J:J) -> Q1 2022
A58: UNIVERSIDAD DE LA IGLESIA DE DEUSTO | B58: Active Customer | C58: High Growth potential | D58: Roman Nacha | E58: Spain | F58: BILBAO | G58: 80523 | H58: 24-09-2022 | I58: 26841 | J58: 23-11-2022 | K58: ="Q" & ROUNDUP(MONTH(J:J)/3,0) & " " & YEAR(J:J) -> Q4 2022 | L58: ="Q" & ROUNDUP(MONTH(J:J)/3,0) & " " & YEAR(J:J) -> Q4 2022
A59: Posicionamiento natural | B59: Not a Customer | C59: No growth Potential | D59: Roman Nacha | E59: Spain | F59: TBD | G59: 67742 | H59: 24-07-2022 | I59: 0 | J59: 44601 | K59: ="Q" & ROUNDUP(MONTH(J:J)/3,0) & " " & YEAR(J:J) -> Q1 2022 | L59: ="Q" & ROUNDUP(MONTH(J:J)/3,0) & " " & YEAR(J:J) -> Q1 2022
A60: NTR | B60: Not a Customer | C60: No growth Potential | D60: Roman Nacha | E60: Spain | F60: A CORUNA | G60: 96217 | H60: 13-10-2022 | I60: 0 | J60: 44603 | K60: ="Q" & ROUNDUP(MONTH(J:J)/3,0) & " " & YEAR(J:J) -> Q1 2022 | L60: ="Q" & ROUNDUP(MONTH(J:J)/3,0) & " " & YEAR(J:J) -> Q1 2022
A61: Emagister | B61: Not a Customer | C61: No growth Potential | D61: Roman Nacha | E61: Spain | F61: Sant Cugat del Valles | G61: 90293 | H61: 44866 | I61: 0 | J61: 44595 | K61: ="Q" & ROUNDUP(MONTH(J:J)/3,0) & " " & YEAR(J:J) -> Q1 2022 | L61: ="Q" & ROUNDUP(MONTH(J:J)/3,0) & " " & YEAR(J:J) -> Q1 2022
A62: Aena | B62: Active Customer | C62: Medium Growth | D62: Roman Nacha | E62: Spain | F62: Madrid | G62: 270429 | H62: 24-03-2022 | I62: 135215 | J62: 23-04-2022 | K62: ="Q" & ROUNDUP(MONTH(J:J)/3,0) & " " & YEAR(J:J) -> Q2 2022 | L62: ="Q" & ROUNDUP(MONTH(J:J)/3,0) & " " & YEAR(J:J) -> Q2 2022
A63: Mellerbrand | B63: Not a Customer | C63: No growth Potential | D63: Roman Nacha | E63: Spain | F63: Barcelona | G63: 63020 | H63: 24-07-2022 | I63: 0 | J63: 44601 | K63: ="Q" & ROUNDUP(MONTH(J:J)/3,0) & " " & YEAR(J:J) -> Q1 2022 | L63: ="Q" & ROUNDUP(MONTH(J:J)/3,0) & " " & YEAR(J:J) -> Q1 2022
A64: GRUPO DANOBAT | B64: Not a Customer | C64: No growth Potential | D64: Roman Nacha | E64: Spain | F64: ELGOIBAR | G64: 71125 | H64: 13-10-2022 | I64: 0 | J64: 44603 | K64: ="Q" & ROUNDUP(MONTH(J:J)/3,0) & " " & YEAR(J:J) -> Q1 2022 | L64: ="Q" & ROUNDUP(MONTH(J:J)/3,0) & " " & YEAR(J:J) -> Q1 2022
A65: BitBan Technologies S.L. | B65: Not a Customer | C65: No growth Potential | D65: Roman Nacha | E65: Spain | F65: Madrid | G65: 48820 | H65: 21-02-2022 | I65: 0 | J65: 44597 | K65: ="Q" & ROUNDUP(MONTH(J:J)/3,0) & " " & YEAR(J:J) -> Q1 2022 | L65: ="Q" & ROUNDUP(MONTH(J:J)/3,0) & " " & YEAR(J:J) -> Q1 2022
A66: Gestion de Publicaciones y Publicidad | B66: Not a Customer | C66: No growth Potential | D66: Roman Nacha | E66: Spain | F66: Madrid | G66: 118761 | H66: 23-05-2023 | I66: 0 | J66: 44963 | K66: ="Q" & ROUNDUP(MONTH(J:J)/3,0) & " " & YEAR(J:J) -> Q1 2023 | L66: ="Q" & ROUNDUP(MONTH(J:J)/3,0) & " " & YEAR(J:J) -> Q1 2023
A67: Trans-Fast Financial Services S.A. | B67: Not a Customer | C67: No growth Potential | D67: Roman Nacha | E67: Spain | F67: TBD | G67: 74208 | H67: 44562 | I67: 0 | J67: 44595 | K67: ="Q" & ROUNDUP(MONTH(J:J)/3,0) & " " & YEAR(J:J) -> Q1 2022 | L67: ="Q" & ROUNDUP(MONTH(J:J)/3,0) & " " & YEAR(J:J) -> Q1 2022
A68: Lextrend | B68: Not a Customer | C68: No growth Potential | D68: Roman Nacha | E68: Spain | F68: Madrid | G68: 62337 | H68: 13-10-2022 | I68: 0 | J68: 44603 | K68: ="Q" & ROUNDUP(MONTH(J:J)/3,0) & " " & YEAR(J:J) -> Q1 2022 | L68: ="Q" & ROUNDUP(MONTH(J:J)/3,0) & " " & YEAR(J:J) -> Q1 2022
A69: Ayuntamiento de Villarana | B69: Not a Customer | C69: No growth Potential | D69: Roman Nacha | E69: Spain | F69: Vallirana | G69: 143588 | H69: 23-04-2022 | I69: 0 | J69: 44598 | K69: ="Q" & ROUNDUP(MONTH(J:J)/3,0) & " " & YEAR(J:J) -> Q1 2022 | L69: ="Q" & ROUNDUP(MONTH(J:J)/3,0) & " " & YEAR(J:J) -> Q1 2022
A70: Mutua Montanesa | B70: Not a Customer | C70: No growth Potential | D70: Roman Nacha | E70: Spain | F70: Santander | G70: 61002 | H70: 44623 | I70: 0 | J70: 44597 | K70: ="Q" & ROUNDUP(MONTH(J:J)/3,0) & " " & YEAR(J:J) -> Q1 2022 | L70: ="Q" & ROUNDUP(MONTH(J:J)/3,0) & " " & YEAR(J:J) -> Q1 2022
A71: Red Inmobiliarias Asturianas (AF Grupo Publicidad y Comunicacion Selecta ) | B71: Not a Customer | C71: No growth Potential | D71: Roman Nacha | E71: Spain | F71: Cayes (Llanera) | G71: 109980 | H71: 44631 | I71: 0 | J71: 44958 | K71: ="Q" & ROUNDUP(MONTH(J:J)/3,0) & " " & YEAR(J:J) -> Q1 2023 | L71: ="Q" & ROUNDUP(MONTH(J:J)/3,0) & " " & YEAR(J:J) -> Q1 2023
A72: trip4real | B72: Not a Customer | C72: No growth Potential | D72: Roman Nacha | E72: Spain | F72: Barcelona | G72: 106526 | H72: 23-07-2022 | I72: 0 | J72: 44600 | K72: ="Q" & ROUNDUP(MONTH(J:J)/3,0) & " " & YEAR(J:J) -> Q1 2022 | L72: ="Q" & ROUNDUP(MONTH(J:J)/3,0) & " " & YEAR(J:J) -> Q1 2022
A73: Grup Serhs | B73: Not a Customer | C73: No growth Potential | D73: Roman Nacha | E73: Spain | F73: Pineda de Mar | G73: 70969 | H73: 44629 | I73: 0 | J73: 44603 | K73: ="Q" & ROUNDUP(MONTH(J:J)/3,0) & " " & YEAR(J:J) -> Q1 2022 | L73: ="Q" & ROUNDUP(MONTH(J:J)/3,0) & " " & YEAR(J:J) -> Q1 2022
A74: GOLDCAR | B74: Not a Customer | C74: No growth Potential | D74: Roman Nacha | E74: Spain | F74: madrid | G74: 100034 | H74: 23-09-2022 | I74: 0 | J74: 44603 | K74: ="Q" & ROUNDUP(MONTH(J:J)/3,0) & " " & YEAR(J:J) -> Q1 2022 | L74: ="Q" & ROUNDUP(MONTH(J:J)/3,0) & " " & YEAR(J:J) -> Q1 2022
A75: L'Arca del Maresme Empresa Inserción SLL | B75: Not a Customer | C75: No growth Potential | D75: Roman Nacha | E75: Spain | F75: Argentona | G75: 107069 | H75: 44629 | I75: 0 | J75: 44603 | K75: ="Q" & ROUNDUP(MONTH(J:J)/3,0) & " " & YEAR(J:J) -> Q1 2022 | L75: ="Q" & ROUNDUP(MONTH(J:J)/3,0) & " " & YEAR(J:J) -> Q1 2022
A76: Dapargel Sl | B76: Not a Customer | C76: No growth Potential | D76: Roman Nacha | E76: Spain | F76: Derio | G76: 143517 | H76: 24-08-2022 | I76: 0 | J76: 44603 | K76: ="Q" & ROUNDUP(MONTH(J:J)/3,0) & " " & YEAR(J:J) -> Q1 2022 | L76: ="Q" & ROUNDUP(MONTH(J:J)/3,0) & " " & YEAR(J:J) -> Q1 2022
A77: intermas group | B77: Not a Customer | C77: No growth Potential | D77: Roman Nacha | E77: Spain | F77: Barcelona | G77: 58504 | H77: 24-08-2022 | I77: 0 | J77: 44603 | K77: ="Q" & ROUNDUP(MONTH(J:J)/3,0) & " " & YEAR(J:J) -> Q1 2022 | L77: ="Q" & ROUNDUP(MONTH(J:J)/3,0) & " " & YEAR(J:J) -> Q1 2022
A78: TMT Spain | B78: Not a Customer | C78: Medium Growth | D78: Roman Nacha | E78: Spain | F78: TBD | G78: 95966 | H78: 44629 | I78: 0 | J78: 44603 | K78: ="Q" & ROUNDUP(MONTH(J:J)/3,0) & " " & YEAR(J:J) -> Q1 2022 | L78: ="Q" & ROUNDUP(MONTH(J:J)/3,0) & " " & YEAR(J:J) -> Q1 2022
A79: STYLE-OUT | B79: Not a Customer | C79: Medium Growth | D79: Roman Nacha | E79: Portugal | F79: Mesão Frio | G79: 54725 | H79: 19-10-2022 | I79: 0 | J79: 44784 | K79: ="Q" & ROUNDUP(MONTH(J:J)/3,0) & " " & YEAR(J:J) -> Q3 2022 | L79: ="Q" & ROUNDUP(MONTH(J:J)/3,0) & " " & YEAR(J:J) -> Q3 2022
A80: FACETZ | B80: Not a Customer | C80: Medium Growth | D80: Roman Nacha | E80: Spain | F80: Barcelona | G80: 147868 | H80: 20-02-2023 | I80: 0 | J80: 44960 | K80: ="Q" & ROUNDUP(MONTH(J:J)/3,0) & " " & YEAR(J:J) -> Q1 2023 | L80: ="Q" & ROUNDUP(MONTH(J:J)/3,0) & " " & YEAR(J:J) -> Q1 2023
A81: Apliscience | B81: Not a Customer | C81: No growth Potential | D81: Roman Nacha | E81: Spain | F81: Barcelona | G81: 112714 | H81: 44868 | I81: 0 | J81: 20-04-2022 | K81: ="Q" & ROUNDUP(MONTH(J:J)/3,0) & " " & YEAR(J:J) -> Q2 2022 | L81: ="Q" & ROUNDUP(MONTH(J:J)/3,0) & " " & YEAR(J:J) -> Q2 2022
A82: CLNICA DENTAL AD | B82: Not a Customer | C82: No growth Potential | D82: Roman Nacha | E82: Spain | F82: TBD | G82: 74208 | H82: 23-10-2022 | I82: 0 | J82: 44603 | K82: ="Q" & ROUNDUP(MONTH(J:J)/3,0) & " " & YEAR(J:J) -> Q1 2022 | L82: ="Q" & ROUNDUP(MONTH(J:J)/3,0) & " " & YEAR(J:J) -> Q1 2022
A83: Volkswagen-Audi Spain | B83: Not a Customer | C83: No growth Potential | D83: Roman Nacha | E83: Spain | F83: TBD | G83: 90068 | H83: 14-12-2022 | I83: 0 | J83: 44959 | K83: ="Q" & ROUNDUP(MONTH(J:J)/3,0) & " " & YEAR(J:J) -> Q1 2023 | L83: ="Q" & ROUNDUP(MONTH(J:J)/3,0) & " " & YEAR(J:J) -> Q1 2023
A84: ANCCE | B84: Not a Customer | C84: No growth Potential | D84: Roman Nacha | E84: Spain | F84: TBD | G84: 80085 | H84: 23-10-2022 | I84: 0 | J84: 44603 | K84: ="Q" & ROUNDUP(MONTH(J:J)/3,0) & " " & YEAR(J:J) -> Q1 2022 | L84: ="Q" & ROUNDUP(MONTH(J:J)/3,0) & " " & YEAR(J:J) -> Q1 2022
A85: TURISMO ANDALUZ | B85: Not a Customer | C85: No growth Potential | D85: Roman Nacha | E85: Spain | F85: MALAGA | G85: 157857 | H85: 23-03-2022 | I85: 0 | J85: 44597 | K85: ="Q" & ROUNDUP(MONTH(J:J)/3,0) & " " & YEAR(J:J) -> Q1 2022 | L85: ="Q" & ROUNDUP(MONTH(J:J)/3,0) & " " & YEAR(J:J) -> Q1 2022
A86: TransHotel Servicios Corporativos S.L.U | B86: Not a Customer | C86: No growth Potential | D86: Roman Nacha | E86: Spain | F86: San Sebastián de los Reyes | G86: 88677 | H86: 44927 | I86: 0 | J86: 44960 | K86: ="Q" & ROUNDUP(MONTH(J:J)/3,0) & " " & YEAR(J:J) -> Q1 2023 | L86: ="Q" & ROUNDUP(MONTH(J:J)/3,0) & " " & YEAR(J:J) -> Q1 2023
A87: Castilla Informatica Consulting | B87: Not a Customer | C87: No growth Potential | D87: Roman Nacha | E87: Spain | F87: Valladolid | G87: 203793 | H87: 13-01-2022 | I87: 0 | J87: 44594 | K87: ="Q" & ROUNDUP(MONTH(J:J)/3,0) & " " & YEAR(J:J) -> Q1 2022 | L87: ="Q" & ROUNDUP(MONTH(J:J)/3,0) & " " & YEAR(J:J) -> Q1 2022
A88: IES Pablo de olavide | B88: Not a Customer | C88: No growth Potential | D88: Roman Nacha | E88: Spain | F88: Carolina | G88: 55037 | H88: 13-10-2022 | I88: 0 | J88: 44603 | K88: ="Q" & ROUNDUP(MONTH(J:J)/3,0) & " " & YEAR(J:J) -> Q1 2022 | L88: ="Q" & ROUNDUP(MONTH(J:J)/3,0) & " " & YEAR(J:J) -> Q1 2022
A89: GRUPO REIG JOFRE | B89: Not a Customer | C89: No growth Potential | D89: Roman Nacha | E89: Spain | F89: BARCELONA | G89: 106786 | H89: 44629 | I89: 0 | J89: 44603 | K89: ="Q" & ROUNDUP(MONTH(J:J)/3,0) & " " & YEAR(J:J) -> Q1 2022 | L89: ="Q" & ROUNDUP(MONTH(J:J)/3,0) & " " & YEAR(J:J) -> Q1 2022
A90: Copreci S. Coop | B90: Not a Customer | C90: No growth Potential | D90: Roman Nacha | E90: Spain | F90: Gipuzkoa | G90: 83160 | H90: 13-11-2022 | I90: 0 | J90: 23-11-2022 | K90: ="Q" & ROUNDUP(MONTH(J:J)/3,0) & " " & YEAR(J:J) -> Q4 2022 | L90: ="Q" & ROUNDUP(MONTH(J:J)/3,0) & " " & YEAR(J:J) -> Q4 2022
A91: MEDIAWAYS SOLUTIONS (MS) | B91: Not a Customer | C91: Medium Growth | D91: Roman Nacha | E91: France | F91: PARIS | G91: 137608 | H91: 13-08-2022 | I91: 0 | J91: 44601 | K91: ="Q" & ROUNDUP(MONTH(J:J)/3,0) & " " & YEAR(J:J) -> Q1 2022 | L91: ="Q" & ROUNDUP(MONTH(J:J)/3,0) & " " & YEAR(J:J) -> Q1 2022
A92: Tressis SV | B92: Not a Customer | C92: Medium Growth | D92: Roman Nacha | E92: Spain | F92: TBD | G92: 157835 | H92: 23-10-2022 | I92: 0 | J92: 44603 | K92: ="Q" & ROUNDUP(MONTH(J:J)/3,0) & " " & YEAR(J:J) -> Q1 2022 | L92: ="Q" & ROUNDUP(MONTH(J:J)/3,0) & " " & YEAR(J:J) -> Q1 2022
A93: Circulo de lectores S.A. | B93: Not a Customer | C93: Medium Growth | D93: Roman Nacha | E93: Spain | F93: Barcelona | G93: 187470 | H93: 22-12-2021 | I93: 0 | J93: 44595 | K93: ="Q" & ROUNDUP(MONTH(J:J)/3,0) & " " & YEAR(J:J) -> Q1 2022 | L93: ="Q" & ROUNDUP(MONTH(J:J)/3,0) & " " & YEAR(J:J) -> Q1 2022
A94: ALTEN | B94: Not a Customer | C94: No growth Potential | D94: Roman Nacha | E94: France | F94: BOULOGNE BILLANCOURT CEDEX | G94: 102196 | H94: 14-03-2022 | I94: 0 | J94: 23-04-2022 | K94: ="Q" & ROUNDUP(MONTH(J:J)/3,0) & " " & YEAR(J:J) -> Q2 2022 | L94: ="Q" & ROUNDUP(MONTH(J:J)/3,0) & " " & YEAR(J:J) -> Q2 2022
A95: Bonacuista BGS S.L. Acuista | B95: Not a Customer | C95: No growth Potential | D95: Roman Nacha | E95: Spain | F95: Barcelona | G95: 100539 | H95: 23-08-2022 | I95: 0 | J95: 44601 | K95: ="Q" & ROUNDUP(MONTH(J:J)/3,0) & " " & YEAR(J:J) -> Q1 2022 | L95: ="Q" & ROUNDUP(MONTH(J:J)/3,0) & " " & YEAR(J:J) -> Q1 2022
A96: Vip Venta | B96: Not a Customer | C96: Medium Growth | D96: Roman Nacha | E96: Spain | F96: Villaviciosa de Odon | G96: 76925 | H96: 13-10-2022 | I96: 0 | J96: 44603 | K96: ="Q" & ROUNDUP(MONTH(J:J)/3,0) & " " & YEAR(J:J) -> Q1 2022 | L96: ="Q" & ROUNDUP(MONTH(J:J)/3,0) & " " & YEAR(J:J) -> Q1 2022
A97: CAIXABANK CONSUMER FINANCE | B97: Not a Customer | C97: No growth Potential | D97: Roman Nacha | E97: Spain | F97: Barcelona | G97: 110085 | H97: 44623 | I97: 0 | J97: 44597 | K97: ="Q" & ROUNDUP(MONTH(J:J)/3,0) & " " & YEAR(J:J) -> Q1 2022 | L97: ="Q" & ROUNDUP(MONTH(J:J)/3,0) & " " & YEAR(J:J) -> Q1 2022
A98: Fundacion cajamadrid | B98: Not a Customer | C98: No growth Potential | D98: Roman Nacha | E98: Spain | F98: madrid | G98: 83580 | H98: 44899 | I98: 0 | J98: 44597 | K98: ="Q" & ROUNDUP(MONTH(J:J)/3,0) & " " & YEAR(J:J) -> Q1 2022 | L98: ="Q" & ROUNDUP(MONTH(J:J)/3,0) & " " & YEAR(J:J) -> Q1 2022
A99: GROUPAUTO UNIÓN IBERICA | B99: Not a Customer | C99: No growth Potential | D99: Roman Nacha | E99: Spain | F99: Madrid | H99: 23-09-2022 | I99: 0 | J99: 44603 | K99: ="Q" & ROUNDUP(MONTH(J:J)/3,0) & " " & YEAR(J:J) -> Q1 2022 | L99: ="Q" & ROUNDUP(MONTH(J:J)/3,0) & " " & YEAR(J:J) -> Q1 2022
A100: Bigmomo | B100: Not a Customer | C100: No growth Potential | D100: Roman Nacha | E100: Spain | F100: TBD | G100: 42045 | H100: 44630 | I100: 0 | J100: 44603 | K100: ="Q" & ROUNDUP(MONTH(J:J)/3,0) & " " & YEAR(J:J) -> Q1 2022 | L100: ="Q" & ROUNDUP(MONTH(J:J)/3,0) & " " & YEAR(J:J) -> Q1 2022
...

Sheet Instructions
B2: Explanation
C3: Given are the sales data for a COLD ENERGY DRINKX operating business of packaged drinking water
C4: They have only one product size bottle costing the same everywhere
C5: This set is a list of all prospects that were targetted by the sales team
C6: Those prospects that purchased the service, are called out as Active Customer in Account status
C7: All lost opportunities are marked "not a customer" in status
C8: Potential Business means the total budget prospect/customer had to be spent on drinking water, most customers have multiple vendors, so they receive only a small share of the total market
C9: Revenue amount is the total business COLD ENERGY DRINKX received from a certain customer
C10: Growth potential tells if the customer will expereince growth as per the Demand analysis
B13: Task
C14: Answer the Questions from management
C16: Compare the sales reps and rank them to be rewarded: Consider following factors and their weightage:
C17: Total Sales volume - 50%
C18: Effciency of Sales: Revenue Won / Potential Revenue - 30%
C19: No. of customers onboarded - 20%
C21: Prepare a quarter on Quarter graph for Sales for all business and top 3 countries
C23: Which country should we open a new Sales office: consider all possible data
C25: Forecast next one year of revenue if :
C26: Each sales rep converts 2% of total potential revenue from their prospect accounts(not customer) | D26: New customer
C27: Repeats all the revenue with current customer | D27: Existing
C28: >> + 30% growth on each high growth account
C29: >>+ 10% growth in each medium growth account
C30: >> 0% in No growth segment
B32: Instructions
C34: Provide a presentation slide format for the answers
C35: Excel sheet showing the caluclations should be available for interview process
C36: email any questions to RAJDEEP GHOSH keeping your recruiting HR in copy

Sheet Sales rep ranking HW -1
A1: Rep wise sales received YOY | G1: Rep wise Potential business YOY | M1: Revenue won/Potential rev = Sales effeciency | R1: Reps wise customers onboarded - YOY
A2: Account Status | B2: Active Customer | G2: Account Status | H2: (All) | M2: Year | R2: Account Status | S2: Active Customer
M3: 21 | N3: 22 | O3: 23 | P3: Grand Total
A4: Account Owner | B4: SUM of Revenue Amount | G4: Account Owner | H4: SUM of Potential Business | M4: =IFERROR(B4/H4,"") | N4: =IFERROR(C4/I4,"") | O4: =IFERROR(D4/J4,"") | P4: =IFERROR(E4/K4,"") | R4: Account Owner | S4: COUNTA of Account Status
A5: Ban Roamer | B5: 1427909 | G5: Ban Roamer | H5: 56632074 | M5: =IFERROR(B5/H5,"") -> 0.025213786 | N5: =IFERROR(C5/I5,"") | O5: =IFERROR(D5/J5,"") | P5: =IFERROR(E5/K5,"") | R5: Ban Roamer | S5: 25
A6: Ben Usioka | B6: 653733 | G6: Ben Usioka | H6: 2377582 | M6: =IFERROR(B6/H6,"") -> 0.27495708 | N6: =IFERROR(C6/I6,"") | O6: =IFERROR(D6/J6,"") | P6: =IFERROR(E6/K6,"") | R6: Ben Usioka | S6: 23
A7: Dorai Kumar | B7: 750470 | G7: Dorai Kumar | H7: 28071241 | M7: =IFERROR(B7/H7,"") -> 0.026734479 | N7: =IFERROR(C7/I7,"") | O7: =IFERROR(D7/J7,"") | P7: =IFERROR(E7/K7,"") | R7: Dorai Kumar | S7: 14
A8: Josh Bolton | B8: 678441 | G8: Josh Bolton | H8: 9009088 | M8: =IFERROR(B8/H8,"") -> 0.075306291 | N8: =IFERROR(C8/I8,"") | O8: =IFERROR(D8/J8,"") | P8: =IFERROR(E8/K8,"") | R8: Josh Bolton | S8: 15
A9: Kaityu Bonolam | B9: 2253431 | G9: Kaityu Bonolam | H9: 7388949 | M9: =IFERROR(B9/H9,"") -> 0.30497314 | N9: =IFERROR(C9/I9,"") | O9: =IFERROR(D9/J9,"") | P9: =IFERROR(E9/K9,"") | R9: Kaityu Bonolam | S9: 62
A10: Naz Ismail | B10: 1081226 | G10: Naz Ismail | H10: 46006703 | M10: =IFERROR(B10/H10,"") -> 0.023501488 | N10: =IFERROR(C10/I10,"") | O10: =IFERROR(D10/J10,"") | P10: =IFERROR(E10/K10,"") | R10: Naz Ismail | S10: 31
A11: Nikita Hareigye | B11: 189158 | G11: Nikita Hareigye | H11: 709183 | M11: =IFERROR(B11/H11,"") -> 0.26672664 | N11: =IFERROR(C11/I11,"") | O11: =IFERROR(D11/J11,"") | P11: =IFERROR(E11/K11,"") | R11: Nikita Hareigye | S11: 6
A12: Rinika Oprah | B12: 201399 | G12: Rinika Oprah | H12: 586979 | M12: =IFERROR(B12/H12,"") -> 0.34311108 | N12: =IFERROR(C12/I12,"") | O12: =IFERROR(D12/J12,"") | P12: =IFERROR(E12/K12,"") | R12: Rinika Oprah | S12: 6 | X12: =ISBLANK(RANK(M5,M5:M12)) -> FALSE
A13: Roman Nacha | B13: 1441132 | G13: Roman Nacha | H13: 112361947 | R13: Roman Nacha | S13: 43
A14: Grand Total | B14: 8676899 | G14: Grand Total | H14: 263143746 | R14: Grand Total | S14: 225
A16: =R16 -> #REF! | H16: =S16 -> #REF! | M16: =T16 -> #REF! | R16: ='[1]Input data'!C3 -> #REF! | S16: ='[1]Input data'!C4 -> #REF! | T16: ='[1]Input data'!C5 -> #REF!
A17: Ranking based on the Sales received by Rep | H17: Ranking based on Sales efficiency | M17: Ranking based on customer onboarded | R17: 3 Factor weightage | U17: Ranking
A18: Account Owner | B18: 21 | C18: 22 | D18: 23 | H18: 21 | I18: 22 | J18: 23 | M18: 21 | N18: 22 | O18: 23 | R18: 21 | S18: 22 | T18: 23 | U18: 21 | V18: 22 | W18: 23
A19: Ban Roamer | B19: =IFERROR(RANK(B4,B$4:B$12),"") | C19: =RANK(C4,C$4:C$12) -> #N/A | D19: =IFERROR(RANK(D4,D$4:D$12),"") | H19: =RANK(M4,M$4:M$12) -> #VALUE! | I19: =IFERROR(RANK(N4,N$4:N$12),"") | J19: =IFERROR(RANK(O4,O$4:O$12),"") | M19: =IFERROR(RANK(S4,S$4:S$12),"") | N19: =IFERROR(RANK(T4,T$4:T$12),"") | O19: =IFERROR(RANK(U4,U$4:U$12),"") | R19: =B19*$R$16+H19*$S$16+M19*$T$16 -> #VALUE! | S19: =C19*$R$16+I19*$S$16+N19*$T$16 -> #N/A | T19: =D19*$R$16+J19*$S$16+O19*$T$16 -> #VALUE! | U19: =_xludf.ifna(RANK(R19,R$19:R$27)+COUNTIF(R$19:R19,R19)-1,"") -> #NAME? | V19: =RANK(S19,S$19:S$27,TRUE) -> #N/A | W19: =RANK(T19,T$19:T$27,TRUE) -> #VALUE!
A20: Ben Usioka | B20: =IFERROR(RANK(B5,B$4:B$12),"") -> 2 | C20: =RANK(C5,C$4:C$12) -> #N/A | D20: =IFERROR(RANK(D5,D$4:D$12),"") | I20: =IFERROR(RANK(N5,N$4:N$12),"") | J20: =IFERROR(RANK(O5,O$4:O$12),"") | M20: =IFERROR(RANK(S5,S$4:S$12),"") -> 3 | N20: =IFERROR(RANK(T5,T$4:T$12),"") | O20: =IFERROR(RANK(U5,U$4:U$12),"") | S20: =C20*$R$16+I20*$S$16+N20*$T$16 -> #N/A | T20: =D20*$R$16+J20*$S$16+O20*$T$16 -> #VALUE! | U20: =_xludf.ifna(RANK(R20,R$19:R$27)+COUNTIF(R$19:R20,R20)-1,"") -> #NAME? | V20: =RANK(S20,S$19:S$27,TRUE) -> #N/A | W20: =RANK(T20,T$19:T$27,TRUE) -> #VALUE!
A21: Dorai Kumar | B21: =IFERROR(RANK(B6,B$4:B$12),"") -> 6 | C21: =RANK(C6,C$4:C$12) -> #N/A | D21: =IFERROR(RANK(D6,D$4:D$12),"") | H21: =IFERROR(RANK(M6,M$4:M$12),"") -> 3 | I21: =IFERROR(RANK(N6,N$4:N$12),"") | J21: =IFERROR(RANK(O6,O$4:O$12),"") | M21: =IFERROR(RANK(S6,S$4:S$12),"") -> 4 | N21: =IFERROR(RANK(T6,T$4:T$12),"") | O21: =IFERROR(RANK(U6,U$4:U$12),"") | R21: =B21*$R$16+H21*$S$16+M21*$T$16 -> #REF! | S21: =C21*$R$16+I21*$S$16+N21*$T$16 -> #N/A | T21: =D21*$R$16+J21*$S$16+O21*$T$16 -> #VALUE! | U21: =_xludf.ifna(RANK(R21,R$19:R$27)+COUNTIF(R$19:R21,R21)-1,"") -> #NAME? | V21: =RANK(S21,S$19:S$27,TRUE) -> #N/A | W21: =RANK(T21,T$19:T$27,TRUE) -> #VALUE!
A22: Josh Bolton | B22: =IFERROR(RANK(B7,B$4:B$12),"") -> 4 | C22: =RANK(C7,C$4:C$12) -> #N/A | D22: =IFERROR(RANK(D7,D$4:D$12),"") | I22: =IFERROR(RANK(N7,N$4:N$12),"") | J22: =IFERROR(RANK(O7,O$4:O$12),"") | M22: =IFERROR(RANK(S7,S$4:S$12),"") -> 6 | N22: =IFERROR(RANK(T7,T$4:T$12),"") | O22: =IFERROR(RANK(U7,U$4:U$12),"") | S22: =C22*$R$16+I22*$S$16+N22*$T$16 -> #N/A | T22: =D22*$R$16+J22*$S$16+O22*$T$16 -> #VALUE! | U22: =_xludf.ifna(RANK(R22,R$19:R$27)+COUNTIF(R$19:R22,R22)-1,"") -> #NAME? | V22: =RANK(S22,S$19:S$27,TRUE) -> #N/A | W22: =RANK(T22,T$19:T$27,TRUE) -> #VALUE!
A23: Kaityu Bonolam | B23: =IFERROR(RANK(B8,B$4:B$12),"") -> 5 | C23: =RANK(C8,C$4:C$12) -> #N/A | D23: =IFERROR(RANK(D8,D$4:D$12),"") | H23: =IFERROR(RANK(M8,M$4:M$12),"") -> 5 | I23: =IFERROR(RANK(N8,N$4:N$12),"") | J23: =IFERROR(RANK(O8,O$4:O$12),"") | M23: =IFERROR(RANK(S8,S$4:S$12),"") -> 5 | N23: =IFERROR(RANK(T8,T$4:T$12),"") | O23: =IFERROR(RANK(U8,U$4:U$12),"") | R23: =B23*$R$16+H23*$S$16+M23*$T$16 -> #REF! | S23: =C23*$R$16+I23*$S$16+N23*$T$16 -> #N/A | T23: =D23*$R$16+J23*$S$16+O23*$T$16 -> #VALUE! | U23: =_xludf.ifna(RANK(R23,R$19:R$27)+COUNTIF(R$19:R23,R23)-1,"") -> #NAME? | V23: =RANK(S23,S$19:S$27,TRUE) -> #N/A | W23: =RANK(T23,T$19:T$27,TRUE) -> #VALUE!
A24: Naz Ismail | B24: =IFERROR(RANK(B9,B$4:B$12),"") -> 1 | C24: =RANK(C9,C$4:C$12) -> #N/A | D24: =IFERROR(RANK(D9,D$4:D$12),"") | H24: =IFERROR(RANK(M9,M$4:M$12),"") -> 2 | I24: =IFERROR(RANK(N9,N$4:N$12),"") | J24: =IFERROR(RANK(O9,O$4:O$12),"") | M24: =IFERROR(RANK(S9,S$4:S$12),"") -> 1 | N24: =IFERROR(RANK(T9,T$4:T$12),"") | O24: =IFERROR(RANK(U9,U$4:U$12),"") | R24: =B24*$R$16+H24*$S$16+M24*$T$16 -> #REF! | S24: =C24*$R$16+I24*$S$16+N24*$T$16 -> #N/A | T24: =D24*$R$16+J24*$S$16+O24*$T$16 -> #VALUE! | U24: =_xludf.ifna(RANK(R24,R$19:R$27)+COUNTIF(R$19:R24,R24)-1,"") -> #NAME? | V24: =RANK(S24,S$19:S$27,TRUE) -> #N/A | W24: =RANK(T24,T$19:T$27,TRUE) -> #VALUE!
A25: Nikita Hareigye | B25: =IFERROR(RANK(B10,B$4:B$12),"") -> 3 | C25: =RANK(C10,C$4:C$12) -> #N/A | D25: =IFERROR(RANK(D10,D$4:D$12),"") | I25: =IFERROR(RANK(N10,N$4:N$12),"") | M25: =IFERROR(RANK(S10,S$4:S$12),"") -> 2 | N25: =IFERROR(RANK(T10,T$4:T$12),"") | O25: =IFERROR(RANK(U10,U$4:U$12),"") | S25: =C25*$R$16+I25*$S$16+N25*$T$16 -> #N/A | T25: =D25*$R$16+J25*$S$16+O25*$T$16 -> #VALUE! | U25: =_xludf.ifna(RANK(R25,R$19:R$27)+COUNTIF(R$19:R25,R25)-1,"") -> #NAME? | V25: =RANK(S25,S$19:S$27,TRUE) -> #N/A | W25: =RANK(T25,T$19:T$27,TRUE) -> #VALUE!
A26: Rinika Oprah | B26: =IFERROR(RANK(B11,B$4:B$12),"") -> 8 | C26: =RANK(C11,C$4:C$12) -> #N/A | D26: =IFERROR(RANK(D11,D$4:D$12),"") | I26: =IFERROR(RANK(N11,N$4:N$12),"") | J26: =IFERROR(RANK(O11,O$4:O$12),"") | M26: =IFERROR(RANK(S11,S$4:S$12),"") -> 7 | N26: =IFERROR(RANK(T11,T$4:T$12),"") | O26: =IFERROR(RANK(U11,U$4:U$12),"") | S26: =C26*$R$16+I26*$S$16+N26*$T$16 -> #N/A | T26: =D26*$R$16+J26*$S$16+O26*$T$16 -> #VALUE! | U26: =_xludf.ifna(RANK(R26,R$19:R$27)+COUNTIF(R$19:R26,R26)-1,"") -> #NAME? | V26: =RANK(S26,S$19:S$27,TRUE) -> #N/A | W26: =RANK(T26,T$19:T$27,TRUE) -> #VALUE!
A27: Roman Nacha | B27: =IFERROR(RANK(B12,B$4:B$12),"") -> 7 | C27: =RANK(C12,C$4:C$12) -> #N/A | D27: =IFERROR(RANK(D12,D$4:D$12),"") | H27: =IFERROR(RANK(M12,M$4:M$12),"") -> 1 | I27: =IFERROR(RANK(N12,N$4:N$12),"") | J27: =IFERROR(RANK(O12,O$4:O$12),"") | M27: =IFERROR(RANK(S12,S$4:S$12),"") -> 7 | N27: =IFERROR(RANK(T12,T$4:T$12),"") | O27: =IFERROR(RANK(U12,U$4:U$12),"") | R27: =B27*$R$16+H27*$S$16+M27*$T$16 -> #REF! | S27: =C27*$R$16+I27*$S$16+N27*$T$16 -> #N/A | T27: =D27*$R$16+J27*$S$16+O27*$T$16 -> #VALUE! | U27: =_xludf.ifna(RANK(R27,R$19:R$27)+COUNTIF(R$19:R27,R27)-1,"") -> #NAME? | V27: =RANK(S27,S$19:S$27,TRUE) -> #N/A | W27: =RANK(T27,T$19:T$27,TRUE) -> #VALUE!

Sheet Pivot Table 4
B1: QOQ Revenue of all 3 years
A2: Account Status | B2: Active Customer | J2: Account Status | K2: Active Customer
A4: Primary Country | B4: SUM of Revenue Amount | J4: Primary Country | K4: SUM of Revenue Amount
A5: Austria | B5: 260699 | J5: Germany | K5: 4039839
A6: Bulgaria | B6: 27890 | J6: Spain | K6: 1398148
A7: Czech Republic | B7: 9129 | J7: France | K7: 1195384
A8: France | B8: 1195384 | J8: Italy | K8: 1052220
A9: Germany | B9: 4039839 | J9: Switzerland | K9: 442933
A10: Hungary | B10: 15999 | J10: Austria | K10: 260699
A11: Italy | B11: 1052220 | J11: Poland | K11: 96596
A12: Poland | B12: 96596 | J12: Romania | K12: 50854
A13: Portugal | B13: 42984 | J13: Portugal | K13: 42984
A14: Romania | B14: 50854 | J14: Bulgaria | K14: 27890
A15: Slovakia | B15: 25158 | J15: Slovakia | K15: 25158
A16: Spain | B16: 1398148 | J16: Hungary | K16: 15999
... A20: Grand Total | B20: 8676899 | J20: Grand Total | K20: 8676899
A25: Account Status | B25: (All) | F25: Account Status | G25: (All) | L25: Account Status | M25: Active Customer | V25: Account Status | W25: (All) | AB25: Account Status | AC25: Active Customer
A27: Account Owner | B27: Revenue amount | F27: Account Owner | G27: COUNTA of Account Name | L27: Account Owner | M27: COUNTA of Account Name | V27: Account Owner | W27: SUM of Potential Business | AB27: Account Owner | AC27: SUM of Potential Business
A28: Ban Roamer | B28: 1427909 | D28: =B28/$B$37 -> 0.16456444 | F28: Ban Roamer | G28: 408 | L28: Ban Roamer | M28: 25 | Q28: 21 | R28: 22 | S28: 23 | T28: Grand Total | V28: Ban Roamer | W28: 56632074 | AB28: Ban Roamer | AC28: 3735594 | AG28: 0.5 | AH28: 0.3 | AI28: 0.2
A29: Ben Usioka | B29: 653733 | D29: =B29/$B$37 -> 0.075341778 | F29: Ben Usioka | G29: 32 | L29: Ben Usioka | M29: 23 | Q29: =IFERROR(M29/G29,"") -> 0.71875 | R29: =IFERROR(N29/H29,"") | S29: =IFERROR(O29/I29,"") | T29: =IFERROR(P29/J29,"") | V29: Ben Usioka | W29: 2377582 | AB29: Ben Usioka | AC29: 2252202 | AG29: =RANK(AF29,AF$29:AF$37) -> #N/A | AH29: =RANK(T29,T$29:T$37) -> #VALUE! | AI29: =RANK(P29,P$29:P$37) -> #N/A | AJ29: =SUMPRODUCT(AG29:AI29,$AG$28:$AI$28) -> #N/A | AK29: =AG29*AG28+AH29*AH28+AI29*AI28 -> #N/A
A30: Dorai Kumar | B30: 750470 | D30: =B30/$B$37 -> 0.086490577 | F30: Dorai Kumar | G30: 246 | L30: Dorai Kumar | M30: 14 | Q30: =IFERROR(M30/G30,"") -> 0.056910569 | R30: =IFERROR(N30/H30,"") | S30: =IFERROR(O30/I30,"") | T30: =IFERROR(P30/J30,"") | V30: Dorai Kumar | W30: 28071241 | AB30: Dorai Kumar | AC30: 1998306 | AG30: =RANK(AF30,AF$29:AF$37) -> #N/A | AH30: =RANK(T30,T$29:T$37) -> #VALUE! | AI30: =RANK(P30,P$29:P$37) -> #N/A | AJ30: =SUMPRODUCT(AG30:AI30,$AG$28:$AI$28) -> #N/A
A31: Josh Bolton | B31: 678441 | D31: =B31/$B$37 -> 0.078189339 | F31: Josh Bolton | G31: 73 | L31: Josh Bolton | M31: 15 | Q31: =IFERROR(M31/G31,"") -> 0.20547945 | R31: =IFERROR(N31/H31,"") | S31: =IFERROR(O31/I31,"") | T31: =IFERROR(P31/J31,"") | V31: Josh Bolton | W31: 9009088 | AB31: Josh Bolton | AC31: 2375176 | AG31: =RANK(AF31,AF$29:AF$37) -> #N/A | AH31: =RANK(T31,T$29:T$37) -> #VALUE! | AI31: =RANK(P31,P$29:P$37) -> #N/A | AJ31: =SUMPRODUCT(AG31:AI31,$AG$28:$AI$28) -> #N/A
A32: Kaityu Bonolam | B32: 2253431 | D32: =B32/$B$37 -> 0.25970465 | F32: Kaityu Bonolam | G32: 75 | L32: Kaityu Bonolam | M32: 62 | Q32: =IFERROR(M32/G32,"") -> 0.82666667 | R32: =IFERROR(N32/H32,"") | S32: =IFERROR(O32/I32,"") | T32: =IFERROR(P32/J32,"") | V32: Kaityu Bonolam | W32: 7388949 | AB32: Kaityu Bonolam | AC32: 6931193 | AG32: =RANK(AF32,AF$29:AF$37) -> #N/A | AH32: =RANK(T32,T$29:T$37) -> #VALUE! | AI32: =RANK(P32,P$29:P$37) -> #N/A | AJ32: =SUMPRODUCT(AG32:AI32,$AG$28:$AI$28) -> #N/A
A33: Naz Ismail | B33: 1081226 | D33: =B33/$B$37 -> 0.12460973 | F33: Naz Ismail | G33: 417 | L33: Naz Ismail | M33: 31 | Q33: =IFERROR(M33/G33,"") -> 0.074340528 | R33: =IFERROR(N33/H33,"") | S33: =IFERROR(O33/I33,"") | T33: =IFERROR(P33/J33,"") | V33: Naz Ismail | W33: 46006703 | AB33: Naz Ismail | AC33: 3225855 | AG33: =RANK(AF33,AF$29:AF$37) -> #N/A | AH33: =RANK(T33,T$29:T$37) -> #VALUE! | AI33: =RANK(P33,P$29:P$37) -> #N/A | AJ33: =SUMPRODUCT(AG33:AI33,$AG$28:$AI$28) -> #N/A
A34: Nikita Hareigye | B34: 189158 | D34: =B34/$B$37 -> 0.021800185 | F34: Nikita Hareigye | G34: 7 | L34: Nikita Hareigye | M34: 6 | Q34: =IFERROR(M34/G34,"") -> 0.85714286 | R34: =IFERROR(N34/H34,"") | S34: =IFERROR(O34/I34,"") | T34: =IFERROR(P34/J34,"") | V34: Nikita Hareigye | W34: 709183 | AB34: Nikita Hareigye | AC34: 649184 | AG34: =RANK(AF34,AF$29:AF$37) -> #N/A | AH34: =RANK(T34,T$29:T$37) -> #VALUE! | AI34: =RANK(P34,P$29:P$37) -> #N/A | AJ34: =SUMPRODUCT(AG34:AI34,$AG$28:$AI$28) -> #N/A
A35: Rinika Oprah | B35: 201399 | D35: =B35/$B$37 -> 0.023210942 | F35: Rinika Oprah | G35: 6 | L35: Rinika Oprah | M35: 6 | Q35: =IFERROR(M35/G35,"") -> 1 | R35: =IFERROR(N35/H35,"") | S35: =IFERROR(O35/I35,"") | T35: =IFERROR(P35/J35,"") | V35: Rinika Oprah | W35: 586979 | AB35: Rinika Oprah | AC35: 586979 | AG35: =RANK(AF35,AF$29:AF$37) -> #N/A | AH35: =RANK(T35,T$29:T$37) -> #VALUE! | AI35: =RANK(P35,P$29:P$37) -> #N/A | AJ35: =SUMPRODUCT(AG35:AI35,$AG$28:$AI$28) -> #N/A
A36: Roman Nacha | B36: 1441132 | D36: =B36/$B$37 -> 0.16608837 | F36: Roman Nacha | G36: 722 | L36: Roman Nacha | M36: 43 | Q36: =IFERROR(M36/G36,"") -> 0.059556787 | R36: =IFERROR(N36/H36,"") | S36: =IFERROR(O36/I36,"") | T36: =IFERROR(P36/J36,"") | V36: Roman Nacha | W36: 112361947 | AB36: Roman Nacha | AC36: 4846499 | AG36: =RANK(AF36,AF$29:AF$37) -> #N/A | AH36: =RANK(T36,T$29:T$37) -> #VALUE! | AI36: =RANK(P36,P$29:P$37) -> #N/A | AJ36: =SUMPRODUCT(AG36:AI36,$AG$28:$AI$28) -> #N/A
A37: Grand Total | B37: 8676899 | F37: Grand Total | G37: 1986 | L37: Grand Total | M37: 225 | Q37: =IFERROR(M37/G37,"") -> 0.11329305 | R37: =IFERROR(N37/H37,"") | S37: =IFERROR(O37/I37,"") | T37: =IFERROR(P37/J37,"") | V37: Grand Total | W37: 263143746 | AB37: Grand Total | AC37: 26600988 | AG37: =RANK(AF37,AF$29:AF$37) -> #N/A | AH37: =RANK(T37,T$29:T$37) -> #VALUE! | AI37: =RANK(P37,P$29:P$37) -> #N/A | AJ37: =SUMPRODUCT(AG37:AI37,$AG$28:$AI$28) -> #N/A
Q38: =IFERROR(M38/G38,"") | R38: =IFERROR(N38/H38,"") | S38: =IFERROR(O38/I38,"") | T38: =IFERROR(P38/J38,"") | AK38: =AG38*AG37+AH38*AH37+AI38*AI37 -> #N/A
W39: 21 | X39: 22 | Y39: 23 | Z39: Grand Total | AC39: =AC38/W38 -> #DIV/0! | AD39: =AD38/X38 -> #DIV/0! | AE39: =AE38/Y38 -> #DIV/0! | AF39: =AF38/Z38 -> #DIV/0! | AK39: =AG39*AG38+AH39*AH38+AI39*AI38 -> 0
W40: Sales effeciency - 30%
V41: Ban Roamer | W41: =IFERROR(AC29/W29,"") -> 0.94726575 | X41: =IFERROR(AD29/X29,"") | Y41: =IFERROR(AE29/Y29,"") | Z41: =IFERROR(AF29/Z29,"")
V42: Ben Usioka | W42: =IFERROR(AC30/W30,"") -> 0.071186949 | X42: =IFERROR(AD30/X30,"") | Y42: =IFERROR(AE30/Y30,"") | Z42: =IFERROR(AF30/Z30,"")
V43: Dorai Kumar | W43: =IFERROR(AC31/W31,"") -> 0.26364222 | X43: =IFERROR(AD31/X31,"") | Y43: =IFERROR(AE31/Y31,"") | Z43: =IFERROR(AF31/Z31,"")
V44: Josh Bolton | W44: =IFERROR(AC32/W32,"") -> 0.93804856 | X44: =IFERROR(AD32/X32,"") | Y44: =IFERROR(AE32/Y32,"") | Z44: =IFERROR(AF32/Z32,"")
V45: Kaityu Bonolam | W45: =IFERROR(AC33/W33,"") -> 0.070117065 | X45: =IFERROR(AD33/X33,"") | Y45: =IFERROR(AE33/Y33,"") | Z45: =IFERROR(AF33/Z33,"")
V46: Naz Ismail | W46: =IFERROR(AC34/W34,"") -> 0.91539701 | X46: =IFERROR(AD34/X34,"") | Y46: =IFERROR(AE34/Y34,"") | Z46: =IFERROR(AF34/Z34,"")
V47: Nikita Hareigye | W47: =IFERROR(AC35/W35,"") -> 1 | X47: =IFERROR(AD35/X35,"") | Y47: =IFERROR(AE35/Y35,"") | Z47: =IFERROR(AF35/Z35,"")
V48: Rinika Oprah | W48: =IFERROR(AC36/W36,"") -> 0.043132921 | X48: =IFERROR(AD36/X36,"") | Y48: =IFERROR(AE36/Y36,"") | Z48: =IFERROR(AF36/Z36,"")
V49: Roman Nacha | W49: =IFERROR(AC37/W37,"") -> 0.10108919 | X49: =IFERROR(AD37/X37,"") | Y49: =IFERROR(AE37/Y37,"") | Z49: =IFERROR(AF37/Z37,"")

Sheet Dashboard
C1: Leads received YOY | F1: Active customers | I1: Conv % | L1: Revenue
A2: Active Customer | B2: {=UNIQUE('Sales Data'!E:E)} -> #NAME? | C2: 21 | D2: 22 | E2: 23 | F2: 21 | G2: 22 | H2: 23 | I2: 21 | J2: 22 | K2: 23 | L2: 21 | M2: 22 | N2: 23
B3: #NAME? | C3: =COUNTIFS('Sales Data'!$E:$E,B3,#REF!,$C$2) -> #REF! | D3: =COUNTIFS('Sales Data'!$E:$E,B3,#REF!,$D$2) -> #REF! | E3: =COUNTIFS('Sales Data'!$E:$E,B3,#REF!,$E$2) -> #REF! | F3: =COUNTIFS('Sales Data'!$E:$E,B3,#REF!,$C$2,'Sales Data'!$B:$B,$A$2) -> #REF! | G3: =COUNTIFS('Sales Data'!$E:$E,B3,#REF!,$G$2,'Sales Data'!$B:$B,$A$2) -> #REF! | H3: =COUNTIFS('Sales Data'!$E:$E,B3,#REF!,$H$2,'Sales Data'!$B:$B,$A$2) -> #REF! | I3: =IFERROR(F3/C3,"") | J3: =IFERROR(G3/D3,"") | K3: =IFERROR(H3/E3,"") | L3: =SUMIFS('Sales Data'!$I:$I,'Sales Data'!$E:$E,$B3,#REF!,$L$2) -> #REF! | M3: =SUMIFS('Sales Data'!$I:$I,'Sales Data'!$E:$E,$B3,#REF!,$M$2) -> #REF! | N3: =SUMIFS('Sales Data'!$I:$I,'Sales Data'!$E:$E,$B3,#REF!,NL$2) -> #REF!
B4: #NAME? | C4: =COUNTIFS('Sales Data'!$E:$E,B4,#REF!,$C$2) -> #REF! | D4: =COUNTIFS('Sales Data'!$E:$E,B4,#REF!,$D$2) -> #REF! | E4: =COUNTIFS('Sales Data'!$E:$E,B4,#REF!,$E$2) -> #REF! | F4: =COUNTIFS('Sales Data'!$E:$E,B4,#REF!,$C$2,'Sales Data'!$B:$B,$A$2) -> #REF! | G4: =COUNTIFS('Sales Data'!$E:$E,B4,#REF!,$G$2,'Sales Data'!$B:$B,$A$2) -> #REF! | H4: =COUNTIFS('Sales Data'!$E:$E,B4,#REF!,$H$2,'Sales Data'!$B:$B,$A$2) -> #REF! | I4: =IFERROR(F4/C4,"") | J4: =IFERROR(G4/D4,"") | K4: =IFERROR(H4/E4,"") | L4: =SUMIFS('Sales Data'!$I:$I,'Sales Data'!$E:$E,$B4,#REF!,$L$2) -> #REF! | M4: =SUMIFS('Sales Data'!$I:$I,'Sales Data'!$E:$E,$B4,#REF!,$M$2) -> #REF! | N4: =SUMIFS('Sales Data'!$I:$I,'Sales Data'!$E:$E,$B4,#REF!,NL$2) -> #REF!
B5: #NAME? | C5: =COUNTIFS('Sales Data'!$E:$E,B5,#REF!,$C$2) -> #REF! | D5: =COUNTIFS('Sales Data'!$E:$E,B5,#REF!,$D$2) -> #REF! | E5: =COUNTIFS('Sales Data'!$E:$E,B5,#REF!,$E$2) -> #REF! | F5: =COUNTIFS('Sales Data'!$E:$E,B5,#REF!,$C$2,'Sales Data'!$B:$B,$A$2) -> #REF! | G5: =COUNTIFS('Sales Data'!$E:$E,B5,#REF!,$G$2,'Sales Data'!$B:$B,$A$2) -> #REF! | H5: =COUNTIFS('Sales Data'!$E:$E,B5,#REF!,$H$2,'Sales Data'!$B:$B,$A$2) -> #REF! | I5: =IFERROR(F5/C5,"") | J5: =IFERROR(G5/D5,"") | K5: =IFERROR(H5/E5,"") | L5: =SUMIFS('Sales Data'!$I:$I,'Sales Data'!$E:$E,$B5,#REF!,$L$2) -> #REF! | M5: =SUMIFS('Sales Data'!$I:$I,'Sales Data'!$E:$E,$B5,#REF!,$M$2) -> #REF! | N5: =SUMIFS('Sales Data'!$I:$I,'Sales Data'!$E:$E,$B5,#REF!,NL$2) -> #REF!
B6: #NAME? | C6: =COUNTIFS('Sales Data'!$E:$E,B6,#REF!,$C$2) -> #REF! | D6: =COUNTIFS('Sales Data'!$E:$E,B6,#REF!,$D$2) -> #REF! | E6: =COUNTIFS('Sales Data'!$E:$E,B6,#REF!,$E$2) -> #REF! | F6: =COUNTIFS('Sales Data'!$E:$E,B6,#REF!,$C$2,'Sales Data'!$B:$B,$A$2) -> #REF! | G6: =COUNTIFS('Sales Data'!$E:$E,B6,#REF!,$G$2,'Sales Data'!$B:$B,$A$2) -> #REF! | H6: =COUNTIFS('Sales Data'!$E:$E,B6,#REF!,$H$2,'Sales Data'!$B:$B,$A$2) -> #REF! | I6: =IFERROR(F6/C6,"") | J6: =IFERROR(G6/D6,"") | K6: =IFERROR(H6/E6,"") | L6: =SUMIFS('Sales Data'!$I:$I,'Sales Data'!$E:$E,$B6,#REF!,$L$2) -> #REF! | M6: =SUMIFS('Sales Data'!$I:$I,'Sales Data'!$E:$E,$B6,#REF!,$M$2) -> #REF! | N6: =SUMIFS('Sales Data'!$I:$I,'Sales Data'!$E:$E,$B6,#REF!,NL$2) -> #REF!
B7: #NAME? | C7: =COUNTIFS('Sales Data'!$E:$E,B7,#REF!,$C$2) -> #REF! | D7: =COUNTIFS('Sales Data'!$E:$E,B7,#REF!,$D$2) -> #REF! | E7: =COUNTIFS('Sales Data'!$E:$E,B7,#REF!,$E$2) -> #REF! | F7: =COUNTIFS('Sales Data'!$E:$E,B7,#REF!,$C$2,'Sales Data'!$B:$B,$A$2) -> #REF! | G7: =COUNTIFS('Sales Data'!$E:$E,B7,#REF!,$G$2,'Sales Data'!$B:$B,$A$2) -> #REF! | H7: =COUNTIFS('Sales Data'!$E:$E,B7,#REF!,$H$2,'Sales Data'!$B:$B,$A$2) -> #REF! | I7: =IFERROR(F7/C7,"") | J7: =IFERROR(G7/D7,"") | K7: =IFERROR(H7/E7,"") | L7: =SUMIFS('Sales Data'!$I:$I,'Sales Data'!$E:$E,$B7,#REF!,$L$2) -> #REF! | M7: =SUMIFS('Sales Data'!$I:$I,'Sales Data'!$E:$E,$B7,#REF!,$M$2) -> #REF! | N7: =SUMIFS('Sales Data'!$I:$I,'Sales Data'!$E:$E,$B7,#REF!,NL$2) -> #REF!
B8: #NAME? | C8: =COUNTIFS('Sales Data'!$E:$E,B8,#REF!,$C$2) -> #REF! | D8: =COUNTIFS('Sales Data'!$E:$E,B8,#REF!,$D$2) -> #REF! | E8: =COUNTIFS('Sales Data'!$E:$E,B8,#REF!,$E$2) -> #REF! | F8: =COUNTIFS('Sales Data'!$E:$E,B8,#REF!,$C$2,'Sales Data'!$B:$B,$A$2) -> #REF! | G8: =COUNTIFS('Sales Data'!$E:$E,B8,#REF!,$G$2,'Sales Data'!$B:$B,$A$2) -> #REF! | H8: =COUNTIFS('Sales Data'!$E:$E,B8,#REF!,$H$2,'Sales Data'!$B:$B,$A$2) -> #REF! | I8: =IFERROR(F8/C8,"") | J8: =IFERROR(G8/D8,"") | K8: =IFERROR(H8/E8,"") | L8: =SUMIFS('Sales Data'!$I:$I,'Sales Data'!$E:$E,$B8,#REF!,$L$2) -> #REF! | M8: =SUMIFS('Sales Data'!$I:$I,'Sales Data'!$E:$E,$B8,#REF!,$M$2) -> #REF! | N8: =SUMIFS('Sales Data'!$I:$I,'Sales Data'!$E:$E,$B8,#REF!,NL$2) -> #REF!
B9: #NAME? | C9: =COUNTIFS('Sales Data'!$E:$E,B9,#REF!,$C$2) -> #REF! | D9: =COUNTIFS('Sales Data'!$E:$E,B9,#REF!,$D$2) -> #REF! | E9: =COUNTIFS('Sales Data'!$E:$E,B9,#REF!,$E$2) -> #REF! | F9: =COUNTIFS('Sales Data'!$E:$E,B9,#REF!,$C$2,'Sales Data'!$B:$B,$A$2) -> #REF! | G9: =COUNTIFS('Sales Data'!$E:$E,B9,#REF!,$G$2,'Sales Data'!$B:$B,$A$2) -> #REF! | H9: =COUNTIFS('Sales Data'!$E:$E,B9,#REF!,$H$2,'Sales Data'!$B:$B,$A$2) -> #REF! | I9: =IFERROR(F9/C9,"") | J9: =IFERROR(G9/D9,"") | K9: =IFERROR(H9/E9,"") | L9: =SUMIFS('Sales Data'!$I:$I,'Sales Data'!$E:$E,$B9,#REF!,$L$2) -> #REF! | M9: =SUMIFS('Sales Data'!$I:$I,'Sales Data'!$E:$E,$B9,#REF!,$M$2) -> #REF! | N9: =SUMIFS('Sales Data'!$I:$I,'Sales Data'!$E:$E,$B9,#REF!,NL$2) -> #REF!
B10: #NAME? | C10: =COUNTIFS('Sales Data'!$E:$E,B10,#REF!,$C$2) -> #REF! | D10: =COUNTIFS('Sales Data'!$E:$E,B10,#REF!,$D$2) -> #REF! | E10: =COUNTIFS('Sales Data'!$E:$E,B10,#REF!,$E$2) -> #REF! | F10: =COUNTIFS('Sales Data'!$E:$E,B10,#REF!,$C$2,'Sales Data'!$B:$B,$A$2) -> #REF! | G10: =COUNTIFS('Sales Data'!$E:$E,B10,#REF!,$G$2,'Sales Data'!$B:$B,$A$2) -> #REF! | H10: =COUNTIFS('Sales Data'!$E:$E,B10,#REF!,$H$2,'Sales Data'!$B:$B,$A$2) -> #REF! | I10: =IFERROR(F10/C10,"") | J10: =IFERROR(G10/D10,"") | K10: =IFERROR(H10/E10,"") | L10: =SUMIFS('Sales Data'!$I:$I,'Sales Data'!$E:$E,$B10,#REF!,$L$2) -> #REF! | M10: =SUMIFS('Sales Data'!$I:$I,'Sales Data'!$E:$E,$B10,#REF!,$M$2) -> #REF! | N10: =SUMIFS('Sales Data'!$I:$I,'Sales Data'!$E:$E,$B10,#REF!,NL$2) -> #REF!
B11: #NAME? | C11: =COUNTIFS('Sales Data'!$E:$E,B11,#REF!,$C$2) -> #REF! | D11: =COUNTIFS('Sales Data'!$E:$E,B11,#REF!,$D$2) -> #REF! | E11: =COUNTIFS('Sales Data'!$E:$E,B11,#REF!,$E$2) -> #REF! | F11: =COUNTIFS('Sales Data'!$E:$E,B11,#REF!,$C$2,'Sales Data'!$B:$B,$A$2) -> #REF! | G11: =COUNTIFS('Sales Data'!$E:$E,B11,#REF!,$G$2,'Sales Data'!$B:$B,$A$2) -> #REF! | H11: =COUNTIFS('Sales Data'!$E:$E,B11,#REF!,$H$2,'Sales Data'!$B:$B,$A$2) -> #REF! | I11: =IFERROR(F11/C11,"") | J11: =IFERROR(G11/D11,"") | K11: =IFERROR(H11/E11,"") | L11: =SUMIFS('Sales Data'!$I:$I,'Sales Data'!$E:$E,$B11,#REF!,$L$2) -> #REF! | M11: =SUMIFS('Sales Data'!$I:$I,'Sales Data'!$E:$E,$B11,#REF!,$M$2) -> #REF! | N11: =SUMIFS('Sales Data'!$I:$I,'Sales Data'!$E:$E,$B11,#REF!,NL$2) -> #REF!
B12: #NAME? | C12: =COUNTIFS('Sales Data'!$E:$E,B12,#REF!,$C$2) -> #REF! | D12: =COUNTIFS('Sales Data'!$E:$E,B12,#REF!,$D$2) -> #REF! | E12: =COUNTIFS('Sales Data'!$E:$E,B12,#REF!,$E$2) -> #REF! | F12: =COUNTIFS('Sales Data'!$E:$E,B12,#REF!,$C$2,'Sales Data'!$B:$B,$A$2) -> #REF! | G12: =COUNTIFS('Sales Data'!$E:$E,B12,#REF!,$G$2,'Sales Data'!$B:$B,$A$2) -> #REF! | H12: =COUNTIFS('Sales Data'!$E:$E,B12,#REF!,$H$2,'Sales Data'!$B:$B,$A$2) -> #REF! | I12: =IFERROR(F12/C12,"") | J12: =IFERROR(G12/D12,"") | K12: =IFERROR(H12/E12,"") | L12: =SUMIFS('Sales Data'!$I:$I,'Sales Data'!$E:$E,$B12,#REF!,$L$2) -> #REF! | M12: =SUMIFS('Sales Data'!$I:$I,'Sales Data'!$E:$E,$B12,#REF!,$M$2) -> #REF! | N12: =SUMIFS('Sales Data'!$I:$I,'Sales Data'!$E:$E,$B12,#REF!,NL$2) -> #REF!
B13: #NAME? | C13: =COUNTIFS('Sales Data'!$E:$E,B13,#REF!,$C$2) -> #REF! | D13: =COUNTIFS('Sales Data'!$E:$E,B13,#REF!,$D$2) -> #REF! | E13: =COUNTIFS('Sales Data'!$E:$E,B13,#REF!,$E$2) -> #REF! | F13: =COUNTIFS('Sales Data'!$E:$E,B13,#REF!,$C$2,'Sales Data'!$B:$B,$A$2) -> #REF! | G13: =COUNTIFS('Sales Data'!$E:$E,B13,#REF!,$G$2,'Sales Data'!$B:$B,$A$2) -> #REF! | H13: =COUNTIFS('Sales Data'!$E:$E,B13,#REF!,$H$2,'Sales Data'!$B:$B,$A$2) -> #REF! | I13: =IFERROR(F13/C13,"") | J13: =IFERROR(G13/D13,"") | K13: =IFERROR(H13/E13,"") | L13: =SUMIFS('Sales Data'!$I:$I,'Sales Data'!$E:$E,$B13,#REF!,$L$2) -> #REF! | M13: =SUMIFS('Sales Data'!$I:$I,'Sales Data'!$E:$E,$B13,#REF!,$M$2) -> #REF! | N13: =SUMIFS('Sales Data'!$I:$I,'Sales Data'!$E:$E,$B13,#REF!,NL$2) -> #REF!
B14: #NAME? | C14: =COUNTIFS('Sales Data'!$E:$E,B14,#REF!,$C$2) -> #REF! | D14: =COUNTIFS('Sales Data'!$E:$E,B14,#REF!,$D$2) -> #REF! | E14: =COUNTIFS('Sales Data'!$E:$E,B14,#REF!,$E$2) -> #REF! | F14: =COUNTIFS('Sales Data'!$E:$E,B14,#REF!,$C$2,'Sales Data'!$B:$B,$A$2) -> #REF! | G14: =COUNTIFS('Sales Data'!$E:$E,B14,#REF!,$G$2,'Sales Data'!$B:$B,$A$2) -> #REF! | H14: =COUNTIFS('Sales Data'!$E:$E,B14,#REF!,$H$2,'Sales Data'!$B:$B,$A$2) -> #REF! | I14: =IFERROR(F14/C14,"") | J14: =IFERROR(G14/D14,"") | K14: =IFERROR(H14/E14,"") | L14: =SUMIFS('Sales Data'!$I:$I,'Sales Data'!$E:$E,$B14,#REF!,$L$2) -> #REF! | M14: =SUMIFS('Sales Data'!$I:$I,'Sales Data'!$E:$E,$B14,#REF!,$M$2) -> #REF! | N14: =SUMIFS('Sales Data'!$I:$I,'Sales Data'!$E:$E,$B14,#REF!,NL$2) -> #REF!
... B25: #NAME? | C25: =COUNTIFS('Sales Data'!$E:$E,B25,#REF!,$C$2) -> #REF! | D25: =COUNTIFS('Sales Data'!$E:$E,B25,#REF!,$D$2) -> #REF! | E25: =COUNTIFS('Sales Data'!$E:$E,B25,#REF!,$E$2) -> #REF! | F25: =COUNTIFS('Sales Data'!$E:$E,B25,#REF!,$C$2,'Sales Data'!$B:$B,$A$2) -> #REF! | G25: =COUNTIFS('Sales Data'!$E:$E,B25,#REF!,$G$2,'Sales Data'!$B:$B,$A$2) -> #REF! | H25: =COUNTIFS('Sales Data'!$E:$E,B25,#REF!,$H$2,'Sales Data'!$B:$B,$A$2) -> #REF! | I25: =IFERROR(F25/C25,"") | J25: =IFERROR(G25/D25,"") | K25: =IFERROR(H25/E25,"") | L25: =SUMIFS('Sales Data'!$I:$I,'Sales Data'!$E:$E,$B25,#REF!,$L$2) -> #REF! | M25: =SUMIFS('Sales Data'!$I:$I,'Sales Data'!$E:$E,$B25,#REF!,$M$2) -> #REF! | N25: =SUMIFS('Sales Data'!$I:$I,'Sales Data'!$E:$E,$B25,#REF!,NL$2) -> #REF!
